Workbook

Sheet BDD
P2: Bail | X2: Financement | AM2: Detention capital € | AQ2: VALORISATION | AS2: Démembrement
A3: SCI | B3: Date d'aquisition | C3: Code postal | D3: Ville | E3: adresse | F3: N°de lot | G3: Destination | H3: surface terrain m² | I3: Surfaces privatives | J3: Usage | K3: Copro | L3: Prix d'acquisition | M3: Description avant travaux | N3: Section cadastre | O3: Type de bail | P3: Locataire | Q3: date de début | R3: date de fin | S3: Loyer annuel de départ | T3: soumis à TVA | U3: indice revalorisation loyers | V3: Loyer annuel actuel HC (07/2025) | W3: Surface louée en m² | X3: Quote part prix d'achat | Y3: Quote part non financé/apport | Z3: TOTAL Emprunts | AA3: VO | AB3: VNC | AC3: Quote part Emprunt | AD3: Quote part Emprunt reste à payer à fin 2025 | AE3: Banques | AF3: Garantie | AG3: Durée | AH3: Date de fin | AI3: Taux d'intérêt | AJ3: Taux d'assurance | AK3: Taux IRA | AL3: Comptes courants débiteurs | AM3: Damien | AN3: Sebastien | AO3: HIO | AP3: AXORIEL | AQ3: sur base 7% de renta | AR3: prix m² | AS3: oui/non
A4: 34 RUE HAUTE | B4: 44558 | C4: 95170 | D4: DEUIL LA BARRE | E4: 34 RUE HAUTE | G4: Crèche | H4: 1265 | K4: non | L4: 380000 | M4: une maison à usage d'habitation et son terrain | N4: AE273;AE1086;AE1177 | O4: commercial | P4: LPC LE LAC | Q4: 44562 | R4: 47848 | S4: 87000 | T4: non | U4: ILC | W4: 395 | X4: =$L$4*W4/SUM($W$4:$W$9) -> 201964.48 | Y4: =33500/SUM($X$4:$X$9)*X4 -> 17804.763 | Z4: =1924000+350000 -> 2274000 | AA4: 2390000 | AB4: 70000 | AC4: =$Z$4/SUM($W$4:$W$9)*W4 -> 1208598 | AD4: =(305557+1175369+308929)/SUM($AC$4:$AC$9)*AC4 -> 951281.92 | AE4: SG et CE | AF4: sur SG caution HIO et AXORIEL sur CE hypothèque et Caution SAS | AG4: 15 CE et 7 SG | AH4: 49836 | AI4: 1,35% CE et 3,53% SG | AJ4: non trouvé | AK4: sur emprunt SG voir formule (environ 6 mois d'intérêt) | AM4: 0.0001 | AN4: 0.0001 | AO4: 0.4999 | AP4: 0.4999
A5: 34 RUE HAUTE | B5: 44558 | C5: 95170 | D5: DEUIL LA BARRE | E5: 34 RUE HAUTE | G5: Ecole | H5: 1265 | K5: non | M5: une maison à usage d'habitation et son terrain | N5: AE273;AE1086;AE1177 | O5: professionnel | P5: CESAP | Q5: 45412 | R5: 48698 | S5: 30600 | T5: non | U5: ICC 4T2023 = 2162 | V5: =S5/2162*2146 -> 30373.543 | W5: 174 | X5: =$L$4*W5/SUM($W$4:$W$9) -> 88966.631 | Y5: =33500/SUM($X$4:$X$9)*X5 -> 7843.1109 | AC5: =$Z$4/SUM($W$4:$W$9)*W5 -> 532395.05 | AD5: =(305557+1175369+308929)/SUM($AC$4:$AC$9)*AC5 -> 419045.71 | AM5: 0.0001 | AN5: 0.0001 | AO5: 0.4999 | AP5: 0.4999
A6: 34 RUE HAUTE | B6: 44558 | C6: 95170 | D6: DEUIL LA BARRE | E6: 34 RUE HAUTE | G6: Logements 1 appartement avec terrasse et jardin RDC | H6: 1265 | K6: non | M6: une maison à usage d'habitation et son terrain | N6: AE273;AE1086;AE1177 | O6: logement | P6: M. BONHOMME | Q6: 45261 | R6: 47452 | S6: =895*12 -> 10740 | T6: non | U6: IRL 3T2023 = 141,03 | W6: 43.4 | X6: =$L$4*W6/SUM($W$4:$W$9) -> 22190.527 | Y6: =33500/SUM($X$4:$X$9)*X6 -> 1956.2702 | AC6: =$Z$4/SUM($W$4:$W$9)*W6 -> 132792.79 | AD6: =(305557+1175369+308929)/SUM($AC$4:$AC$9)*AC6 -> 104520.6 | AM6: 0.0001 | AN6: 0.0001 | AO6: 0.4999 | AP6: 0.4999
A7: 34 RUE HAUTE | B7: 44558 | C7: 95170 | D7: DEUIL LA BARRE | E7: 34 RUE HAUTE | G7: Logements 2 appartement RDC | H7: 1265 | K7: non | M7: une maison à usage d'habitation et son terrain | N7: AE273;AE1086;AE1177 | O7: logement | P7: M. LEPAGE | Q7: 45234 | R7: 47425 | S7: =590*12 -> 7080 | T7: non | U7: IRL 3T2023 = 141,03 | W7: 27.7 | X7: =$L$4*W7/SUM($W$4:$W$9) -> 14163.079 | Y7: =33500/SUM($X$4:$X$9)*X7 -> 1248.5872 | AC7: =$Z$4/SUM($W$4:$W$9)*W7 -> 84754.844 | AD7: =(305557+1175369+308929)/SUM($AC$4:$AC$9)*AC7 -> 66710.15 | AM7: 0.0001 | AN7: 0.0001 | AO7: 0.4999 | AP7: 0.4999
A8: 34 RUE HAUTE | B8: 44558 | C8: 95170 | D8: DEUIL LA BARRE | E8: 34 RUE HAUTE | G8: Logements 3 1er étage à droite | H8: 1265 | K8: non | M8: une maison à usage d'habitation et son terrain | N8: AE273;AE1086;AE1177 | O8: logement | P8: Mme CHERIF | Q8: 45428 | R8: 47618 | S8: =870*12 -> 10440 | T8: non | U8: IRL 1T2024 = 143,46 | W8: 45.4 | X8: =$L$4*W8/SUM($W$4:$W$9) -> 23213.132 | Y8: =33500/SUM($X$4:$X$9)*X8 -> 2046.4209 | AC8: =$Z$4/SUM($W$4:$W$9)*W8 -> 138912.27 | AD8: =(305557+1175369+308929)/SUM($AC$4:$AC$9)*AC8 -> 109337.21 | AM8: 0.0001 | AN8: 0.0001 | AO8: 0.4999 | AP8: 0.4999
A9: 34 RUE HAUTE | B9: 44558 | C9: 95170 | D9: DEUIL LA BARRE | E9: 34 RUE HAUTE | G9: Logements 4 1er étage à gauche | H9: 1265 | K9: non | M9: une maison à usage d'habitation et son terrain | N9: AE273;AE1086;AE1177 | O9: logement | P9: M. SAIDI | Q9: 45444 | R9: 47634 | S9: =1065*12 -> 12780 | T9: non | U9: IRL 1T2024 = 143,46 | W9: 57.7 | X9: =$L$4*W9/SUM($W$4:$W$9) -> 29502.153 | Y9: =33500/SUM($X$4:$X$9)*X9 -> 2600.8477 | AC9: =$Z$4/SUM($W$4:$W$9)*W9 -> 176547.09 | AD9: =(305557+1175369+308929)/SUM($AC$4:$AC$9)*AC9 -> 138959.41 | AM9: 0.0001 | AN9: 0.0001 | AO9: 0.4999 | AP9: 0.4999
A10: LEGRAND | B10: 42965 | C10: 93160 | D10: NOISY LE GRAND | E10: 12 BD DU MONT D'EST | G10: Crèche Noisy | H10: =5050+6587 -> 11637 | I10: 231.1 | J10: bureaux | K10: oui | L10: 250000 | M10: immeuble de 5 étages avec parking jardin et cour | N10: BO168 et BO163 | O10: commercial | P10: LPC LE GRAND | Q10: 43191 | R10: 46843 | S10: 31284 | T10: non | U10: ILC 2T2017 = 110 | V10: =9720.79*4 -> 38883.16 | W10: 231.1 | X10: 250000 | Y10: =3893.7+16283 -> 20176.7 | Z10: 250000 | AC10: =Z10 -> 250000 | AD10: 5217 | AE10: BNP | AF10: Cautionnement de la SAS + privilège de prêteur de deniers | AG10: 8 | AH10: 46071 | AI10: 0.0134 | AJ10: non trouvé | AK10: 0.005 | AM10: 0.5 | AN10: 0.5 | AO10: 0 | AP10: 0 | AS10: oui usufruit SAS
A11: LEGRAND | B11: 43284 | C11: 92330 | D11: SCEAUX | E11: 146/148 RUE HOUDAN | G11: Crèche Sceaux | H11: 807 | I11: 192.6 | J11: commercial | K11: oui | L11: 780000 | M11: immeuble | N11: E174 | O11: commercial | P11: LPC SCEAUX | Q11: 43282 | R11: 46934 | S11: 62000 | T11: non | U11: ILC 1T2018 = 127,22 | V11: =17723.51*4 -> 70894.04 | W11: 192 | X11: 780000 | Y11: 114430 | Z11: 780000 | AC11: =Z11 -> 780000 | AD11: 421889 | AE11: SG | AF11: Cautionnement de la SAS (546k€) | AG11: =180/12 -> 15 | AH11: 48763 | AI11: 0.0189 | AJ11: non trouvé | AK11: page 70 à priori plus rien à partir 03/01/2026 | AM11: 0.5 | AN11: 0.5 | AO11: 0 | AP11: 0 | AS11: oui usufruit SAS
A12: ARMEE ORIENT | B12: 44751 | C12: 78680 | D12: EPONE | E12: Route de Velannes | G12: Crèche Epone | I12: 398.1 | K12: non | L12: 352908 | M12: ensemble immobilier formé par un local d'activité et son jardin | N12: J1451-1641-1473-1477-1478-1482-1481-1486-1480 | O12: commercial | P12: LPC MEDERIC | Q12: 44927 | R12: 49340 | S12: 59090 | T12: non | U12: ILC | V12: =15220*4 -> 60880 | W12: 311 | X12: =L12 -> 352908 | Z12: =AC12 -> 377612 | AC12: 377612 | AD12: 309356 | AE12: LCL | AF12: Affectation hypothécaire du bien immobilier | AG12: 15 | AH12: 50228 | AI12: 0.018 | AJ12: 0.00087 | AM12: 0.0001 | AN12: 0.0001 | AO12: 0.4999 | AP12: 0.4999
A13: ARMEE ORIENT | B13: 44749 | C13: 06300 | D13: NICE | E13: 8 rue Armée D'Orient | G13: Crèche Nice | K13: oui | L13: 665000 | O13: commercial | P13: LPC FREJUS | Q13: 44927 | R13: 48244 | S13: 55000 | T13: non | U13: ILC | V13: =15012.39*4 -> 60049.56 | W13: 201 | X13: =L13 -> 665000 | Z13: 665000 | AC13: =Z13 -> 665000 | AD13: 553110 | AE13: CA | AF13: Hypothèque conventionnelle + Cautionnements solidaires HIO et AXORIEL | AG13: 15 | AH13: 50469 | AI13: 0.014 | AJ13: non trouvé | AK13: 2 mois d'intérêt sur le capital remboursé ou formule | AM13: 0.0001 | AN13: 0.0001 | AO13: 0.4999 | AP13: 0.4999
A14: CHENNEVIERES | B14: Vefa le 01/07/2022 | C14: 94430 | D14: CHENNEVIERES SUR MARNE | E14: 49 rue Aristide Briand | G14: Crèche Chennevières | I14: 206.34 | L14: 734000 | O14: commercial | P14: LPC VAL DE MARNE | Q14: 45170 | R14: 48822 | S14: 75240 | T14: non | U14: ILC | V14: =19672.44*4 -> 78689.76 | W14: 206 | Z14: 734000 | AC14: =Z14 -> 734000 | AD14: 685859 | AE14: LCL | AF14: Affectation hypothécaire du bien immobilier | AG14: 15 | AH14: 50614 | AI14: 0.046 | AJ14: non trouvé | AK14: 1 semestre d'intérêts au taux conventionnel sur le montant remboursé | AM14: 0.0001 | AN14: 0.0001 | AO14: 0.4999 | AP14: 0.4999
A15: CHENNEVIERES | B15: 45055 | C15: 94140 | D15: ALFORTVILLE | E15: 105 rue Etienne Dolet | G15: Crèche Alforville | I15: 311.4 | K15: oui | L15: 840000 | M15: Local commercial | O15: commercial | P15: LPC VAL DE MARNE | Q15: 45292 | R15: 45291 | S15: 86100 | T15: non | U15: ILC | V15: =22177.22*4 -> 88708.88 | W15: 311.4 | X15: =L15 -> 840000 | Y15: =899210.68+6061.35-X15 -> 65272.03 | Z15: 840000 | AC15: =Z15 -> 840000 | AD15: 792257 | AE15: SG | AF15: IPPD et hypothèque. | AG15: 15 | AH15: 50724 | AI15: 0.0453 | AJ15: non trouvé | AK15: voir formule (environ 6 mois d'intérêt) | AM15: 0.0001 | AN15: 0.0001 | AO15: 0.4999 | AP15: 0.4999
A16: TAVERNY | B16: 44889 | C16: 95150 | D16: TAVERNY | E16: 3 rue des Ecoles | G16: Crèche Taverny | I16: 417.97 | K16: oui | L16: 1337730.6 | M16: ensemble immobilier | P16: LPC TAVERNY | Q16: 46266 | S16: 67000 | X16: =L16 -> 1337730.6 | Z16: 1408923 | AC16: =Z16 -> 1408923 | AD16: 1408923 | AE16: CE | AF16: Affectation hypothécaire du bien immobilier | AG16: 20 | AH16: 53332 | AI16: 0.0404 | AJ16: 0.00327 | AK16: non trouvé | AM16: 0.0001 | AN16: 0.0001 | AO16: 0.4999 | AP16: 0.4999
A17: GENERAL JULES BRIMONT | B17: 45128 | C17: 78400 | D17: CHATOU | E17: 32 avenue de Brimont | G17: Crèche Chatou | I17: 387.83 | K17: oui | L17: 1200000 | M17: Local à usage d'activité | N17: AR39-42 | O17: commercial | P17: LPC YVELINES | Q17: 45170 | R17: 48457 | S17: 84000 | T17: non | U17: ILC | V17: =21962.85*4 -> 87851.4 | W17: 258.7 | X17: =$L$17/SUM($W$17:$W$22)*W17 -> 897744.36 | Y17: =108673/(SUM($X$17:$X$22))*X17 -> 81300.477 | Z17: 1200000 | AC17: =X17 -> 897744.36 | AD17: =1092668/SUM($AC$17:$AC$22)*AC17 -> 817447.11 | AE17: CE | AF17: Affectation hypothécaire du bien immobilier | AG17: 15.5 | AH17: 50795 | AI17: 0.051 | AJ17: non trouvé | AK17: non trouvé | AM17: 0.0001 | AN17: 0.0001 | AO17: 0.4999 | AP17: 0.4999
A18: GENERAL JULES BRIMONT | B18: 45128 | C18: 78400 | D18: CHATOU | E18: 30 ter avenue de Brimont | G18: Bureau au RDC | K18: oui | M18: Local à usage d'activité | O18: dérogatoire au statut des baux commerciaux | P18: Petits Fils (Pierre Jacques & Co) | Q18: 45717 | R18: 46812 | S18: =905.44*12 -> 10865.28 | T18: non | U18: ILC 3T2024 | V18: =S18 -> 10865.28 | W18: 15.2 | X18: =$L$17/SUM($W$17:$W$22)*W18 -> 52747.253 | Y18: =108673/(SUM($X$17:$X$22))*X18 -> 4776.8352 | AC18: =X18 -> 52747.253 | AD18: =1092668/SUM($AC$17:$AC$22)*AC18 -> 48029.363 | AM18: 0.0001 | AN18: 0.0001 | AO18: 0.4999 | AP18: 0.4999
A19: GENERAL JULES BRIMONT | B19: 45128 | C19: 78400 | D19: CHATOU | E19: 30 ter avenue de Brimont | G19: Local professionnel | K19: oui | M19: Local à usage d'activité | O19: professionnel | P19: Mme BARREIRO(diététicienne) | Q19: 45895 | R19: 48085 | S19: 3185 | T19: non | U19: ICC 4T2024 = 2108 | V19: =S19 -> 3185 | W19: 11.15 | X19: =$L$17/SUM($W$17:$W$22)*W19 -> 38692.886 | Y19: =108673/(SUM($X$17:$X$22))*X19 -> 3504.06 | AC19: =X19 -> 38692.886 | AD19: =1092668/SUM($AC$17:$AC$22)*AC19 -> 35232.065
A20: GENERAL JULES BRIMONT | B20: 45128 | C20: 78400 | D20: CHATOU | E20: 30 ter avenue de Brimont | G20: Local professionnel | K20: oui | M20: Local à usage d'activité | O20: professionnel | P20: Mme JOUBERT (Psychomotricienne) | Q20: 45895 | R20: 48085 | S20: 11788.32 | T20: non | U20: ICC 3T2024 = 2143 | V20: =S20 -> 11788.32 | W20: 16.5 | X20: =$L$17/SUM($W$17:$W$22)*W20 -> 57258.531 | Y20: =108673/(SUM($X$17:$X$22))*X20 -> 5185.3803 | AC20: =X20 -> 57258.531 | AD20: =1092668/SUM($AC$17:$AC$22)*AC20 -> 52137.137 | AM20: 0.0001 | AN20: 0.0001 | AO20: 0.4999 | AP20: 0.4999
A21: GENERAL JULES BRIMONT | B21: 45128 | C21: 78400 | D21: CHATOU | E21: 30 ter avenue de Brimont | G21: Bureau au RDC | H21: Bureau au RDC | J21: Bureau au RDC | K21: Bureau au RDC | M21: Local à usage d'activité | O21: commercial | P21: Mme DENANT (Pédicure) | Q21: 42676 | R21: =Q21+365.25*9 -> 45963.25 | S21: 7084 | T21: non | U21: ILAT | V21: =699.33*12 -> 8391.96 | W21: 33 | X21: =$L$17/SUM($W$17:$W$22)*W21 -> 114517.06 | Y21: =108673/(SUM($X$17:$X$22))*X21 -> 10370.761 | AC21: =X21 -> 114517.06 | AD21: =1092668/SUM($AC$17:$AC$22)*AC21 -> 104274.27 | AM21: 0.0001 | AN21: 0.0001 | AO21: 0.4999 | AP21: 0.4999
A22: GENERAL JULES BRIMONT | B22: 45128 | C22: 78400 | D22: CHATOU | E22: 30 ter avenue de Brimont | G22: Bureau au RDC | H22: Bureau au RDC | J22: Bureau au RDC | K22: Bureau au RDC | M22: Local à usage d'activité | O22: professionnel | P22: Mme DIAZ COURTENAY MAYERS (Pédopsy) | Q22: 45792 | R22: 45791 | S22: 8040.24 | T22: non | U22: ICC 4T2024 = 2108 | V22: =S22 -> 8040.24 | W22: 11.25 | X22: =$L$17/SUM($W$17:$W$22)*W22 -> 39039.907 | Y22: =108673/(SUM($X$17:$X$22))*X22 -> 3535.4866 | AC22: =X22 -> 39039.907 | AD22: =1092668/SUM($AC$17:$AC$22)*AC22 -> 35548.048 | AM22: 0.0001 | AN22: 0.0001 | AO22: 0.4999 | AP22: 0.4999
A23: GENERAL JULES BRIMONT | B23: 45205 | C23: 95130 | D23: PLESSIS BOUCHARD | E23: 56 Chaussée Jules César | G23: Crèche LPB | L23: 740000 | M23: Maison individuelle | O23: commercial | P23: SARL VAL D'OISE | Q23: 45292 | R23: 48944 | S23: 80000 | T23: non | U23: ILC | V23: =20606.02*4 -> 82424.08 | W23: 396.34 | X23: 740000 | Y23: 65750 | Z23: =X23 -> 740000 | AC23: =Z23 -> 740000 | AD23: 686767 | AE23: LCL | AF23: Hypothèque Légale Spéciale de Prêteur de Deniers sur le bien immobilier | AG23: 15 | AH23: 50684 | AI23: 0.46 | AJ23: non trouvé | AK23: 1 semestre d'intérêts au taux conventionnel sur le montant remboursé | AM23: 0.0001 | AN23: 0.0001 | AO23: 0.4999 | AP23: 0.4999
A26: HOCHE ERMONT | B26: VENDU | AM26: 0.0001 | AN26: 0.0001 | AO26: 0.4999 | AP26: 0.4999
A27: MADELI | B27: VENDU | AM27: 0.0001 | AN27: 0.0001 | AO27: 0.4999 | AP27: 0.4999
A28: 22 RUE ARAGO | B28: VENDU | AM28: 0.5 | AN28: 0.5 | AO28: 0 | AP28: 0 | AS28: oui usufruit SAS | AT28: Vendu

Sheet Feuil1
A3: SCI | B3: Banques | C3: Garantie
A4: 34 RUE HAUTE | B4: SG et CE | C4: sur SG caution HIO et AXORIEL sur CE hypothèque et Caution solidaire de la SAS
A10: LEGRAND | B10: BNP | C10: Cautionnement de la SAS + privilège de prêteur de deniers
A11: LEGRAND | B11: SG | C11: Cautionnement de la SAS (546k€)
A12: ARMEE ORIENT | B12: LCL | C12: Affectation hypothécaire du bien immobilier
A13: ARMEE ORIENT | B13: CA | C13: Hypothèque conventionnelle + Cautionnements solidaires HIO et AXORIEL
A14: CHENNEVIERES | B14: LCL | C14: Affectation hypothécaire du bien immobilier
A15: CHENNEVIERES | B15: SG | C15: IPPD et hypothèque.
A16: TAVERNY | B16: CE | C16: Affectation hypothécaire du bien immobilier
A17: GENERAL JULES BRIMONT | B17: CE | C17: Affectation hypothécaire du bien immobilier
A23: GENERAL JULES BRIMONT | B23: LCL | C23: Hypothèque Légale Spéciale de Prêteur de Deniers sur le bien immobilier

Sheet SCI 34 RUE HAUTE
A1: SCI 34 RUE HAUTE
C4: nb m² | D4: LOCATIONS | E4: 2023 | F4: 2024 | G4: 2025 | H4: 2026
D5: =BDD!D4&" "&BDD!G4 -> DEUIL LA BARRE Crèche | H5: =BDD!S4 -> 87000
D6: =BDD!D5&" "&BDD!G5 -> DEUIL LA BARRE Ecole | H6: =BDD!S5 -> 30600
D7: =BDD!D6&" "&BDD!G6 -> DEUIL LA BARRE Logements 1 appartement avec terrasse et jardin RDC | H7: =BDD!S6 -> 10740
D8: =BDD!D7&" "&BDD!G7 -> DEUIL LA BARRE Logements 2 appartement RDC | H8: =BDD!S7 -> 7080
D9: =BDD!D8&" "&BDD!G8 -> DEUIL LA BARRE Logements 3 1er étage à droite | H9: =BDD!S8 -> 10440
D10: =BDD!D9&" "&BDD!G9 -> DEUIL LA BARRE Logements 4 1er étage à gauche | H10: =BDD!S9 -> 12780
D11: Location 7
D12: Location 8
D13: Location 9
D14: Location 10
D16: CHARGES LOCATIVES | E16: 2023 | F16: 2024 | G16: 2025 | H16: 2026
D17: =D5 -> DEUIL LA BARRE Crèche
D18: =D6 -> DEUIL LA BARRE Ecole
D19: =D7 -> DEUIL LA BARRE Logements 1 appartement avec terrasse et jardin RDC
D20: =D8 -> DEUIL LA BARRE Logements 2 appartement RDC
D21: =D9 -> DEUIL LA BARRE Logements 3 1er étage à droite
D22: =D10 -> DEUIL LA BARRE Logements 4 1er étage à gauche
D23: =D11 -> Location 7
D24: =D12 -> Location 8
D25: =D13 -> Location 9
D26: =D14 -> Location 10
E29: 2023 | F29: 2024 | G29: 2025 | H29: 2026
D31: PRODUCTION VENDUE DE SERVICES (Chiffre d'affaires) | E31: =SUM(E32:E35) -> 105549 | F31: =SUM(F32:F35) -> 174596 | G31: =SUM(G32:G35) -> 202520 | H31: =SUM(H32:H35) -> 206570.4 | J31: =G31/0.07 -> 2893142.9
D32: 70650000 LOYERS CRECHES | E32: 91673 | F32: 97146 | G32: 100089 | H32: =G32*(1+I32) -> 102090.78 | I32: 0.02 | J32: =G32/0.07 -> 1429842.9
D33: 70651000 LOYERS LOGEMENTS + ASSOC. | E33: 3698 | F33: 63428 | G33: =176716-G32 -> 76627 | H33: =G33*(1+I33) -> 78159.54 | I33: 0.02 | J33: =G33/0.07 -> 1094671.4
D34: 70880000 REFACT. CH. - CRECHES | E34: 9805 | F34: 7523 | G34: 16931 | H34: =G34*(1+I34) -> 17269.62 | I34: 0.02 | J34: =G34/0.07 -> 241871.43
D35: 70881000 REFACT. CH- LOGEMENTS + ASSO | E35: 373 | F35: 6499 | G35: =25804-G34 -> 8873 | H35: =G35*(1+I35) -> 9050.46 | I35: 0.02 | J35: =G35/0.07 -> 126757.14
D36: AUTRES PRODUITS | E36: =E37 -> 0 | F36: =F37 -> 0 | G36: =G37 -> 4081 | H36: =H37 -> 0 | J36: =G36/0.07 -> 58300
D37: 75800000 PRODUITS DE GESTION COURANTE | E37: 0 | F37: 0 | G37: 4081 | J37: =G37/0.07 -> 58300
D38: Total des Produits d'exploitation | E38: =E37+E31 -> 105549 | F38: =F37+F31 -> 174596 | G38: =G37+G31 -> 206601 | H38: =H37+H31 -> 206570.4 | J38: =G38/0.07 -> 2951442.9
D39: AUTRES ACHATS ET CHARGES EXTERNES | E39: =SUM(E40:E54) -> 36340 | F39: =SUM(F40:F54) -> 27181 | G39: =SUM(G40:G54) -> 32240.37 | H39: =SUM(H40:H54) -> 32887.166
D40: 60611000 EDF | E40: 1976 | F40: 3206 | G40: 1860.2 | H40: =AVERAGE(E40:G40)*(1+I40) -> 2394.348 | I40: 0.02
D41: 60612000 EAU | E41: 2562 | F41: 3339 | G41: 3387 | H41: =AVERAGE(E41:G41)*(1+I41) -> 3157.92 | I41: 0.02
D42: 60613000 GAZ | E42: 894 | F42: 328 | H42: =AVERAGE(E42:G42)*(1+I42) -> 623.22 | I42: 0.02
D43: 60630000 PETITS OUTILLAGES | E43: 1510 | F43: 0 | H43: =AVERAGE(E43:G43)*(1+I43) -> 770.1 | I43: 0.02
D44: 61420000 CHARGES LOCATIVES - LOG.+ ASSO | E44: 270 | F44: 2399 | G44: 3046 | H44: =G44*(1+I44) -> 3106.92 | I44: 0.02
D45: 61510000 ENTRETIEN ET REPARATION CRECHE | F45: 816 | H45: =AVERAGE(E45:G45)*(1+I45) -> 832.32 | I45: 0.02
D46: 61520000 ENTRETIEN ET REPARATION LOG+AS | F46: 120 | H46: =AVERAGE(E46:G46)*(1+I46) -> 122.4 | I46: 0.02
D47: 61600000 ASSURANCE LOYERS - LOG.+ ASSO. | E47: 81 | F47: 923 | G47: 1030 | H47: =AVERAGE(E47:G47)*(1+I47) -> 691.56 | I47: 0.02
D48: 61600300 ASSURANCE MULTIRISQUE | F48: 87 | G48: 95.5 | H48: =AVERAGE(E48:G48)*(1+I48) -> 93.075 | I48: 0.02
D49: 62260000 HONORAIRES COMPTABLES | E49: 1781 | F49: 1440 | G49: 1555 | H49: =G49*(1+I49) -> 1586.1 | I49: 0.02
D50: 62262000 HONORAIRES JURIDIQUES | E50: 297 | F50: 306 | G50: 330 | H50: =G50*(1+I50) -> 336.6 | I50: 0.02
D51: 62268000 HONORAIRES DIVERS | E51: 25655 | H51: =G51*(1+I51) -> 0 | I51: 0.02
D52: 62268200 HONORAIRES GESTION - LOG.+ASS | F52: 13888 | G52: 18503.67 | H52: =G52*(1+I52) -> 18873.743 | I52: 0.02
D53: 62270000 FRAIS D'ACTES ET CONTENCIEUX | E53: 987 | F53: 70 | I53: 0.02
D54: 62780000 FRAIS BANCAIRES | E54: 327 | F54: 259 | G54: 2433 | H54: =AVERAGE(E54:F54)*(1+I54) -> 298.86 | I54: 0.02
D55: IMPOTS, TAXES ET VERSEMENTS ASSIMILES | E55: =E56+E57 -> 7243 | F55: =F56+F57 -> 13510 | G55: =G56+G57 -> 17368 | H55: =H56+H57 -> 17681.18
D56: 63512000 TAXE FONCIERES | E56: 7243 | F56: 11894 | G56: 15659 | H56: =G56*(1+I56) -> 15972.18 | I56: 0.02
D57: 63513000 TAXE ORDURES MENAGERES et autres | F57: 1616 | G57: 1709 | H57: =G57*(1+I57) -> 1709
D58: DOTATIONS AUX AMORTISSEMENTS SUR IMMOBILISATIONS | E58: =E59 -> 69238 | F58: =F59 -> 103791 | G58: =G59 -> 103791 | H58: =H59 -> 103791
D59: 68112000 DOTATION AMORT. IMMOB.CORP. | E59: 69238 | F59: 103791 | G59: 103791 | H59: =G59 -> 103791
D60: AUTRES CHARGES | E60: =E61 -> 0 | F60: =F61 -> 22 | G60: =G61 -> 0 | H60: =H61 -> 0
D61: 65800000 CHARGES DE GESTION COURANTE | E61: 0 | F61: 22
D62: Total des Charges d'exploitation | E62: =E60+E58+E55+E39 -> 112821 | F62: =F60+F58+F55+F39 -> 144504 | G62: =G60+G58+G55+G39 -> 153399.37 | H62: =H60+H58+H55+H39 -> 154359.35
D63: Résultat d'exploitation | E63: =E38-E62 -> -7272 | F63: =F38-F62 -> 30092 | G63: =G38-G62 -> 53201.63 | H63: =H38-H62 -> 52211.054
D64: INTERETS ET CHARGES ASSIMILEES | E64: =E65+E66 -> 24358 | F64: =F65+F66 -> 22623 | G64: =G65+G66 -> 22142 | H64: =H65+H66 -> 20671.38
D65: 66100000 INTERETS BANCAIRES | F65: 7 | G65: 1
D66: 66112000 INTERETS DES EMPRUNTS - CE | E66: 24358 | F66: 22616 | G66: 22141 | H66: =-Emprunts!BH7-Emprunts!BH8 -> 20671.38
D67: Total des Charges financières | E67: =E64 -> 24358 | F67: =F64 -> 22623 | G67: =G64 -> 22142 | H67: =H64 -> 20671.38
D68: Résultat financier | E68: =E67 -> 24358 | F68: =F67 -> 22623 | G68: =G67 -> 22142 | H68: =H67 -> 20671.38
D69: Résultat courant avant impôts | E69: =E63-E68 -> -31630 | F69: =F63-F68 -> 7469 | G69: =G63-G68 -> 31059.63 | H69: =H63-H68 -> 31539.674
D70: 69500000 IS
D71: Résultat NET | E71: =E69-E70 -> -31630 | F71: =F69-F70 -> 7469 | G71: =G69-G70 -> 31059.63 | H71: =H69-H70 -> 31539.674
D73: IMMOBILISATIONS VO | E73: =SUM(E74:E84) -> 2364237 | F73: =SUM(F74:F84) -> 2384011 | G73: =SUM(G74:G84) -> 2389717 | H73: =SUM(H74:H84) -> 0
D74: TERRAIN | E74: 380000 | F74: 380000 | G74: 380000
D75: AGENCEMENTS TERRAIN | E75: 97721 | F75: 90581
D76: GROS ŒUVRE CRECHE | E76: 417069 | F76: 429276 | G76: 889577
D77: GROS ŒUVRE LOGEMENTS | E77: 472509 | F77: 485310
D78: FACADE ETANCHEITE CRECHE | E78: 167485 | F78: 167485 | G78: 167485
D79: FACADE ETANCHEITE LOGEMENTS | E79: 118205 | F79: 118205 | G79: 118205
D80: INSTALLATIONS CRECHE | E80: 255694 | F80: 255694 | G80: 255694
D81: INSTALLATIONS LOGEMENTS | E81: 274743 | F81: 274743 | G81: 274743
D82: AGENCEMENTS CRECHE | E82: 83984 | F82: 83984 | G82: 278531
D83: AGENCEMENTS LOGEMENTS | E83: 87483 | F83: 87483 | G83: 17867
D84: AGENCEMENTS SUPPL LOGEMENTS | E84: 9344 | F84: 11250 | G84: 7615
D86: FINANCEMENTS IMMO | E86: =SUM(E87:E92) -> 2444262 | F86: =SUM(F87:F92) -> 2451099 | G86: =SUM(G87:G92) -> 1924000 | H86: =SUM(H87:H92) -> 0
D87: EMPRUNT CE VO | E87: 409000 | F87: 409000 | G87: 409000
D88: EMPRUNT CE VO | E88: 1515000 | F88: 1515000 | G88: 1515000
D89: C/C GROUPE
D90: C/C HIO SARLU | E90: 132554 | F90: 255743
D91: C/C AXORIEL SARLU | E91: 133554 | F91: 256743
D92: DETTE FRS | E92: 254154 | F92: 14613
B95: Année fin | C95: Taux | D95: DETTES RESTANTES | E95: =SUM(E96:E107) -> 2305890 | F95: =SUM(F96:F107) -> 2183392 | G95: =SUM(G96:G107) -> 1789854.4 | H95: =SUM(H96:H107) -> 1610125.6
B96: 2035 | C96: 0.0135 | D96: EMPRUNT CE 409k€ | E96: 361377 | F96: 333655 | G96: =Emprunts!V6 -> 305556.77 | H96: =Emprunts!X6 -> 277076.48
B97: 2036 | C97: 0.0135 | D97: EMPRUNT CE 1515k€ | E97: 1380978 | F97: 1278867 | G97: =Emprunts!V7 -> 1175368.8 | H97: =Emprunts!X7 -> 1070464.9
B98: 2032 | C98: 0.0353 | D98: EMPRUNT SG 350k€ | G98: =Emprunts!V8 -> 308928.85 | H98: =Emprunts!X8 -> 262584.23
D99: DG LOGEMENTS | E99: 2355 | F99: 9585
D100: DG CRECHE | E100: 22918 | F100: 24287
D101: C/C GROUPE
D102: C/C HIO SARLU | E102: 132554 | F102: 255743
D103: C/C AXORIEL SARLU | E103: 133554 | F103: 256743
D104: CLIENTS AV ET ACPTES RECUS | E104: 18000 | F104: 3912
D105: DETTES FRS | E105: 254154 | F105: 14613
D106: DETTES FISCALES ET SOCIALES | E106: 0 | F106: 4625
D107: AUTRES DETTES | E107: 0 | F107: 1362
D109: VALORISATION DES BIENS | E109: =SUM(E110:E119) -> 0 | F109: =SUM(F110:F119) -> 0 | G109: =SUM(G110:G119) -> 0 | H109: =SUM(H110:H119) -> 0
D110: ESTIMATION A LA VALEUR DU MARCHE
D111: =D5 -> DEUIL LA BARRE Crèche | E111: 0 | F111: 0 | G111: 0
...

Sheet SCI LEGRAND
A1: SCI LEGRAND
C4: nb m² | D4: LOCATIONS | E4: 2023 | F4: 2024 | G4: 2025 | H4: 2026
D5: =BDD!G10 -> Crèche Noisy | H5: =BDD!S10 -> 31284
D6: =BDD!G11 -> Crèche Sceaux | H6: =BDD!S11 -> 62000
D7: Location 3
D8: Location 4
D9: Location 5
D10: Location 6
D11: Location 7
D12: Location 8
D13: Location 9
D14: Location 10
D16: CHARGES LOCATIVES | E16: 2023 | F16: 2024 | G16: 2025 | H16: 2026
D17: =D5 -> Crèche Noisy
D18: =D6 -> Crèche Sceaux
D19: =D7 -> Location 3
D20: =D8 -> Location 4
D21: =D9 -> Location 5
D22: =D10 -> Location 6
D23: =D11 -> Location 7
D24: =D12 -> Location 8
D25: =D13 -> Location 9
D26: =D14 -> Location 10
E29: 2023 | F29: 2024 | G29: 2025 | H29: 2026
D31: PRODUCTION VENDUE DE SERVICES (Chiffre d'affaires) | E31: =SUM(E32:E35) -> 143563 | F31: =SUM(F32:F35) -> 172786 | G31: =SUM(G32:G35) -> 156065 | H31: =SUM(H32:H35) -> 159186.3
D32: 70650000 LOYERS CRECHES | E32: =34794+66410 -> 101204 | F32: =36907+68733 -> 105640 | G32: 108938 | H32: =G32*(1+I32) -> 111116.76 | I32: 0.02
D33: 70651000 LOYERS LOGEMENTS + ASSOC. | H33: =G33*(1+I33) -> 0 | I33: 0.02
D34: 70880000 REFACT. CH. - CRECHES | E34: =19253+23106 -> 42359 | F34: =28552+38594 -> 67146 | G34: 47127 | H34: =G34*(1+I34) -> 48069.54 | I34: 0.02
D35: 70881000 REFACT. CH- LOGEMENTS + ASSO | H35: =G35*(1+I35) -> 0 | I35: 0.02
D36: AUTRES PRODUITS | E36: =E37 -> 0 | F36: =F37 -> 174 | G36: =G37 -> 0 | H36: =H37 -> 0
D37: 75800000 PRODUITS DE GESTION COURANTE | E37: 0 | F37: 174 | G37: 0
D38: Total des Produits d'exploitation | E38: =E37+E31 -> 143563 | F38: =F37+F31 -> 172960 | G38: =G37+G31 -> 156065 | H38: =H37+H31 -> 159186.3
D39: AUTRES ACHATS ET CHARGES EXTERNES | E39: =SUM(E40:E54) -> 45453 | F39: =SUM(F40:F54) -> 41674 | G39: =SUM(G40:G54) -> 44201.7 | H39: =SUM(H40:H54) -> 44839.778
D40: 60611000 EDF | I40: 0.02
D41: 60612000 EAU | I41: 0.02
D42: 60613000 GAZ | I42: 0.02
D43: 60630000 PETITS OUTILLAGES | I43: 0.02
D44: 61420000 CHARGES LOCATIVES - LOG.+ ASSO | E44: =15587+19891 -> 35478 | F44: =11387+22813 -> 34200 | G44: 36665 | H44: =G44*(1+I44) -> 37398.3 | I44: 0.02
D45: 61510000 ENTRETIEN ET REPARATION CRECHE | E45: =2630+3877 -> 6507 | F45: =3159-1159 -> 2000 | G45: 4602.7 | H45: =AVERAGE(E45:G45)*(1+I45) -> 4457.298 | I45: 0.02
D46: 61520000 ENTRETIEN ET REPARATION LOG+AS | I46: 0.02
D47: 61600000 ASSURANCE LOYERS - LOG.+ ASSO. | E47: =98+705 -> 803 | F47: =37+761 -> 798 | G47: 860 | H47: =AVERAGE(E47:G47)*(1+I47) -> 836.74 | I47: 0.02
D48: 61600300 ASSURANCE MULTIRISQUE | I48: 0.02
D49: 62260000 HONORAIRES COMPTABLES | E49: 1576 | F49: 1607 | G49: 1498 | H49: =G49*(1+I49) -> 1527.96 | I49: 0.02
D50: 62262000 HONORAIRES JURIDIQUES | E50: 692 | F50: 299 | G50: 247 | H50: =G50*(1+I50) -> 251.94 | I50: 0.02
D51: 62268000 HONORAIRES DIVERS | F51: 2415 | H51: =G51*(1+I51) -> 0 | I51: 0.02
D52: 62268200 HONORAIRES GESTION - LOG.+ASS | H52: =G52*(1+I52) -> 0 | I52: 0.02
D53: 62270000 FRAIS D'ACTES ET CONTENCIEUX | I53: 0.02
D54: 62780000 FRAIS BANCAIRES | E54: 397 | F54: 355 | G54: 329 | H54: =AVERAGE(E54:G54)*(1+I54) -> 367.54 | I54: 0.02
D55: IMPOTS, TAXES ET VERSEMENTS ASSIMILES | E55: =E56+E57 -> 10397 | F55: =F56+F57 -> 10821 | G55: =G56+G57 -> 10940 | H55: =H56+H57 -> 11158.8
D56: 63512000 TAXE FONCIERES | E56: 10397 | F56: 10821 | G56: 10940 | H56: =G56*(1+I56) -> 11158.8 | I56: 0.02
D57: 63513000 TAXE ORDURES MENAGERES | H57: =G57*(1+I57) -> 0
D58: DOTATIONS AUX AMORTISSEMENTS SUR IMMOBILISATIONS | E58: =E59 -> 37085 | F58: =F59 -> 37085 | G58: =G59 -> 37085 | H58: =H59 -> 37085
D59: 68112000 DOTATION AMORT. IMMOB.CORP. | E59: 37085 | F59: 37085 | G59: 37085 | H59: =G59 -> 37085
D60: AUTRES CHARGES | E60: =E61 -> 0 | F60: =F61 -> 105 | G60: =G61 -> 0 | H60: =H61 -> 0
D61: 65800000 CHARGES DE GESTION COURANTE | F61: 105
D62: Total des Charges d'exploitation | E62: =E60+E58+E55+E39 -> 92935 | F62: =F60+F58+F55+F39 -> 89685 | G62: =G60+G58+G55+G39 -> 92226.7 | H62: =H60+H58+H55+H39 -> 93083.578
D63: Résultat d'exploitation | E63: =E38-E62 -> 50628 | F63: =F38-F62 -> 83275 | G63: =G38-G62 -> 63838.3 | H63: =H38-H62 -> 66102.722
D64: INTERETS ET CHARGES ASSIMILEES | E64: =E65+E66 -> 12099 | F64: =F65+F66 -> 10869 | G64: =G65+G66 -> 9161 | H64: =H65+H66 -> 7522.7425
D65: 66100000 INTERETS BANCAIRES
D66: 66112000 INTERETS DES EMPRUNTS - CE | E66: 12099 | F66: 10869 | G66: 9161 | H66: =-Emprunts!BH12 -> 7522.7425
D67: Total des Charges financières | E67: =E64 -> 12099 | F67: =F64 -> 10869 | G67: =G64 -> 9161 | H67: =H64 -> 7522.7425
D68: Résultat financier | E68: =E67 -> 12099 | F68: =F67 -> 10869 | G68: =G67 -> 9161 | H68: =H67 -> 7522.7425
D69: Résultat courant avant impôts | E69: =E63-E68 -> 38529 | F69: =F63-F68 -> 72406 | G69: =G63-G68 -> 54677.3 | H69: =H63-H68 -> 58579.979
D70: 69500000 IS
D71: Résultat NET | E71: =E69-E70 -> 38529 | F71: =F69-F70 -> 72406 | G71: =G69-G70 -> 54677.3 | H71: =H69-H70 -> 58579.979
D73: IMMOBILISATIONS VO | E73: =SUM(E74:E84) -> 1030000 | F73: =SUM(F74:F84) -> 1030000 | G73: =SUM(G74:G84) -> 1030000 | H73: =SUM(H74:H84) -> 0
D74: TERRAIN | E74: 206000 | F74: 206000 | G74: 206000
D75: AGENCEMENTS TERRAIN
D76: GROS ŒUVRE CRECHE | E76: 412000 | F76: 412000 | G76: 412000
D77: GROS ŒUVRE LOGEMENTS
D78: FACADE ETANCHEITE CRECHE | E78: 206000 | F78: 206000 | G78: 206000
D79: FACADE ETANCHEITE LOGEMENTS
D80: INSTALLATIONS CRECHE | E80: 123600 | F80: 123600 | G80: 123600
D81: INSTALLATIONS LOGEMENTS
D82: AGENCEMENTS CRECHE | E82: 82400 | F82: 82400 | G82: 82400
D83: AGENCEMENTS LOGEMENTS
D84: AGENCEMENTS SUPPL LOGEMENTS
D86: FINANCEMENTS IMMO | E86: =SUM(E87:E92) -> 1020000 | F86: =SUM(F87:F92) -> 1020000 | G86: =SUM(G87:G92) -> 1020000 | H86: =SUM(H87:H92) -> 0
D87: =D96 -> EMPRUNT BNP 240k€ | E87: 240000 | F87: 240000 | G87: 240000
D88: =D97 -> EMPRUNT SG 780k€ | E88: 780000 | F88: 780000 | G88: 780000
D89: C/C GROUPE
D90: C/C HIO SARLU
D91: C/C AXORIEL SARLU
D92: DETTE FRS
B95: Année fin | C95: Taux | D95: DETTES RESTANTES | E95: =SUM(E96:E107) -> 741152 | F95: =SUM(F96:F107) -> 647705 | G95: =SUM(G96:G107) -> 610620 | H95: =SUM(H96:H107) -> 0
B96: 2026 | C96: 0.01 | D96: EMPRUNT BNP 240k€ | E96: 67820 | F96: 36518 | G96: 5217
B97: 2033 | C97: 0.0189 | D97: EMPRUNT SG 780k€ | E97: 523449 | F97: 473148 | G97: 421888
D98: Emprunt
D99: DG LOGEMENTS
D100: DG CRECHE | E100: 22749 | F100: 23726 | G100: 24204
D101: C/C GROUPE | E101: 110829 | F101: 109358 | G101: 149178
D102: C/C HIO SARLU
D103: C/C AXORIEL SARLU
D104: CLIENTS AV ET ACPTES RECUS | E104: 3000 | G104: 9522
D105: DETTES FRS | E105: 12438 | F105: 4227
D106: DETTES FISCALES ET SOCIALES
D107: AUTRES DETTES | E107: 867 | F107: 728 | G107: 611
D109: VALORISATION DES BIENS | E109: =SUM(E110:E119) -> 0 | F109: =SUM(F110:F119) -> 0 | G109: =SUM(G110:G119) -> 0 | H109: =SUM(H110:H119) -> 0
D110: ESTIMATION A LA VALEUR DU MARCHE
D111: =D5 -> Crèche Noisy | E111: 0 | F111: 0 | G111: 0
...

Sheet SCI ARMEE ORIENT
A1: SCI ARMEE ORIENT
C4: nb m² | D4: LOCATIONS | E4: 2023 | F4: 2024 | G4: 2025 | H4: 2026
D5: =BDD!G12 -> Crèche Epone | H5: =BDD!S12 -> 59090
D6: =BDD!G13 -> Crèche Nice | H6: =BDD!S13 -> 55000
D7: Location 3
D8: Location 4
D9: Location 5
D10: Location 6
D11: Location 7
D12: Location 8
D13: Location 9
D14: Location 10
D16: CHARGES LOCATIVES | E16: 2023 | F16: 2024 | G16: 2025 | H16: 2026
D17: =D5 -> Crèche Epone
D18: =D6 -> Crèche Nice
D19: =D7 -> Location 3
D20: =D8 -> Location 4
D21: =D9 -> Location 5
D22: =D10 -> Location 6
D23: =D11 -> Location 7
D24: =D12 -> Location 8
D25: =D13 -> Location 9
D26: =D14 -> Location 10
G28: ok bilan
E29: 2023 | F29: 2024 | G29: 2025 | H29: 2026
D31: PRODUCTION VENDUE DE SERVICES (Chiffre d'affaires) | E31: =SUM(E32:E35) -> 130281 | F31: =SUM(F32:F35) -> 127589 | G31: =SUM(G32:G35) -> 134224 | H31: =SUM(H32:H35) -> 136908.48
D32: 70650000 LOYERS CRECHES | E32: =72500+45833 -> 118333 | F32: =59090+58284 -> 117374 | G32: =60880+60050 -> 120930 | H32: =G32*(1+I32) -> 123348.6 | I32: 0.02 | J32: =G32/0.07 -> 1727571.4
D33: 70651000 LOYERS LOGEMENTS + ASSOC. | H33: =G33*(1+I33) -> 0 | I33: 0.02
D34: 70880000 REFACT. CH. - CRECHES | E34: =7250+4698 -> 11948 | F34: =7189+3026 -> 10215 | G34: =7901+5393 -> 13294 | H34: =G34*(1+I34) -> 13559.88 | I34: 0.02
D35: 70881000 REFACT. CH- LOGEMENTS + ASSO | H35: =G35*(1+I35) -> 0 | I35: 0.02
D36: AUTRES PRODUITS | E36: =E37 -> 0 | F36: =F37 -> 0 | G36: =G37 -> 0 | H36: =H37 -> 0
D37: 75800000 PRODUITS DE GESTION COURANTE | E37: 0 | G37: 0
D38: Total des Produits d'exploitation | E38: =E37+E31 -> 130281 | F38: =F37+F31 -> 127589 | G38: =G37+G31 -> 134224 | H38: =H37+H31 -> 136908.48
D39: AUTRES ACHATS ET CHARGES EXTERNES | E39: =SUM(E40:E54) -> 16996 | F39: =SUM(F40:F54) -> 12398 | G39: =SUM(G40:G54) -> 11693 | H39: =SUM(H40:H54) -> 12024.78
D40: 60611000 EDF | I40: 0.02
D41: 60612000 EAU | I41: 0.02
D42: 60613000 GAZ | I42: 0.02
D43: 60630000 PETITS OUTILLAGES | I43: 0.02
D44: 61420000 CHARGES LOCATIVES - LOG.+ ASSO | E44: =4055+2176 -> 6231 | F44: =2823+3123 -> 5946 | G44: =3191+3075+1 -> 6267 | H44: =G44*(1+I44) -> 6392.34 | I44: 0.02
D45: 61510000 ENTRETIEN ET REPARATION CRECHE | F45: 36 | H45: =AVERAGE(E45:G45)*(1+I45) -> 36.72 | I45: 0.02
D46: 61520000 ENTRETIEN ET REPARATION LOG+AS | I46: 0.02
D47: 61600000 ASSURANCE LOYERS - LOG.+ ASSO. | E47: 371 | F47: 402 | G47: 410 | H47: =G47*(1+I47) -> 418.2 | I47: 0.02
D48: 61600300 ASSURANCE MULTIRISQUE | I48: 0.02
D49: 62260000 HONORAIRES COMPTABLES | E49: 2958 | F49: 1435 | G49: 1557 | H49: =G49*(1+I49) -> 1588.14 | I49: 0.02
D50: 62262000 HONORAIRES JURIDIQUES | E50: 342 | F50: 327 | G50: 331 | H50: =G50*(1+I50) -> 337.62 | I50: 0.02
D51: 62268000 HONORAIRES DIVERS | E51: 5192 | F51: 3483 | G51: 2415 | H51: =G51*(1+I51) -> 2463.3 | I51: 0.02
D52: 62268200 HONORAIRES GESTION - LOG.+ASS | H52: =G52*(1+I52) -> 0 | I52: 0.02
D53: 62270000 FRAIS D'ACTES ET CONTENCIEUX | E53: 1065 | I53: 0.02
D54: 62780000 FRAIS BANCAIRES | E54: 837 | F54: 769 | G54: 713 | H54: =AVERAGE(E54:G54)*(1+I54) -> 788.46 | I54: 0.02
D55: IMPOTS, TAXES ET VERSEMENTS ASSIMILES | E55: =E56+E57 -> 115 | F55: 9834 | G55: =G56+G57 -> 7028 | H55: =H56+H57 -> 7168.56
D56: 63512000 TAXE FONCIERES | E56: 115 | F56: 9384 | G56: 7028 | H56: =G56*(1+I56) -> 7168.56 | I56: 0.02
D57: 63513000 TAXE ORDURES MENAGERES | H57: =G57*(1+I57) -> 0
D58: DOTATIONS AUX AMORTISSEMENTS SUR IMMOBILISATIONS | E58: =E59 -> 32070 | F58: =F59 -> 32070 | G58: =G59 -> 32070 | H58: =H59 -> 32070
D59: 68112000 DOTATION AMORT. IMMOB.CORP. | E59: 32070 | F59: 32070 | G59: 32070 | H59: =G59 -> 32070
D60: AUTRES CHARGES | E60: =E61 -> 0 | F60: =F61 -> 0 | G60: =G61 -> 0 | H60: =H61 -> 0
D61: 65800000 CHARGES DE GESTION COURANTE
D62: Total des Charges d'exploitation | E62: =E60+E58+E55+E39 -> 49181 | F62: =F60+F58+F55+F39 -> 54302 | G62: =G60+G58+G55+G39 -> 50791 | H62: =H60+H58+H55+H39 -> 51263.34
D63: Résultat d'exploitation | E63: =E38-E62 -> 81100 | F63: =F38-F62 -> 73287 | G63: =G38-G62 -> 83433 | H63: =H38-H62 -> 85645.14
D64: INTERETS ET CHARGES ASSIMILEES | E64: =E65+E66 -> 16237 | F64: =F65+F66 -> 14933 | G64: =G65+G66 -> 13904 | H64: =H65+H66 -> 12845.229
D65: 66100000 INTERETS BANCAIRES
D66: 66112000 INTERETS DES EMPRUNTS - CE | E66: 16237 | F66: 14933 | G66: 13904 | H66: =-Emprunts!BH13-Emprunts!BH14 -> 12845.229
D67: Total des Charges financières | E67: =E64 -> 16237 | F67: =F64 -> 14933 | G67: =G64 -> 13904 | H67: =H64 -> 12845.229
D68: Résultat financier | E68: =E67 -> 16237 | F68: =F67 -> 14933 | G68: =G67 -> 13904 | H68: =H67 -> 12845.229
D69: Résultat courant avant impôts | E69: =E63-E68 -> 64863 | F69: =F63-F68 -> 58354 | G69: =G63-G68 -> 69529 | H69: =H63-H68 -> 72799.911
D70: 69500000 IS
D71: Résultat NET | E71: =E69-E70 -> 64863 | F71: =F69-F70 -> 58354 | G71: =G69-G70 -> 69529 | H71: =H69-H70 -> 72799.911
D73: IMMOBILISATIONS VO | E73: =SUM(E74:E84) -> 1017908 | F73: =SUM(F74:F84) -> 1017908 | G73: =SUM(G74:G84) -> 1017908 | H73: =SUM(H74:H84) -> 0
D74: TERRAIN | E74: 305372 | F74: 305372 | G74: 305372
D75: AGENCEMENTS TERRAIN
D76: GROS ŒUVRE CRECHE | E76: 356268 | F76: 356268 | G76: 356268
D77: GROS ŒUVRE LOGEMENTS
D78: FACADE ETANCHEITE CRECHE | E78: 178134 | F78: 178134 | G78: 178134
D79: FACADE ETANCHEITE LOGEMENTS
D80: INSTALLATIONS CRECHE | E80: 106880 | F80: 106880 | G80: 106880
D81: INSTALLATIONS LOGEMENTS
D82: AGENCEMENTS CRECHE | E82: 71254 | F82: 71254 | G82: 71254
D83: AGENCEMENTS LOGEMENTS
D84: AGENCEMENTS SUPPL LOGEMENTS
D86: FINANCEMENTS IMMO | E86: =SUM(E87:E92) -> 1042612 | F86: =SUM(F87:F92) -> 1042612 | G86: =SUM(G87:G92) -> 1042612 | H86: =H80-H81 -> 0
D87: =D96 -> EMPRUNT LCL 377k€ | E87: 377612 | F87: 377612 | G87: 377612
D88: =D97 -> EMPRUNT CA 665k€ | E88: 665000 | F88: 665000 | G88: 665000
D89: C/C GROUPE
D90: C/C HIO SARLU
D91: C/C AXORIEL SARLU
D92: DETTE FRS
B95: Année fin | C95: Taux | D95: DETTES RESTANTES | E95: =SUM(E96:E107) -> 991576 | F95: =SUM(F96:F107) -> 927716 | G95: =SUM(G96:G107) -> 862830 | H95: =SUM(H96:H107) -> 0
B96: 2037 | C96: 0.018 | D96: EMPRUNT LCL 377k€ | E96: 356545 | F96: 333162 | G96: 309356
B97: 2038 | C97: 0.014 | D97: EMPRUNT CA 665k€ | E97: 635031 | F97: 594554 | G97: 553474
D98: Emprunt
D99: DG LOGEMENTS
D100: DG CRECHE
D101: C/C GROUPE
D102: C/C HIO SARLU
D103: C/C AXORIEL SARLU
D104: CLIENTS AV ET ACPTES RECUS
D105: DETTES FRS
D106: DETTES FISCALES ET SOCIALES
D107: AUTRES DETTES
D109: VALORISATION DES BIENS | E109: =SUM(E110:E119) -> 0 | F109: =SUM(F110:F119) -> 0 | G109: =SUM(G110:G119) -> 0 | H109: =SUM(H110:H119) -> 0
D110: ESTIMATION A LA VALEUR DU MARCHE
...

Sheet SCI CHENNEVIERES
A1: SCI CHENNEVIERES
C4: nb m² | D4: LOCATIONS | E4: 2023 | F4: 2024 | G4: 2025 | H4: 2026
D5: =BDD!G14 -> Crèche Chennevières | H5: =BDD!S14 -> 75240
D6: =BDD!G15 -> Crèche Alforville | H6: =BDD!S15 -> 86100
D7: Location 3
D8: Location 4
D9: Location 5
D10: Location 6
D11: Location 7
D12: Location 8
D13: Location 9
D14: Location 10
D16: CHARGES LOCATIVES | E16: 2023 | F16: 2024 | G16: 2025 | H16: 2026
D17: =D5 -> Crèche Chennevières
D18: =D6 -> Crèche Alforville
D19: =D7 -> Location 3
D20: =D8 -> Location 4
D21: =D9 -> Location 5
D22: =D10 -> Location 6
D23: =D11 -> Location 7
D24: =D12 -> Location 8
D25: =D13 -> Location 9
D26: =D14 -> Location 10
G28: ok bilan
E29: 2023 | F29: 2024 | G29: 2025 | H29: 2026
D31: PRODUCTION VENDUE DE SERVICES (Chiffre d'affaires) | E31: =SUM(E32:E35) -> 0 | F31: =SUM(F32:F35) -> 103516 | G31: =SUM(G32:G35) -> 185609 | H31: =SUM(H32:H35) -> 189321.18
D32: 70650000 LOYERS CRECHES | F32: =57580+28544 -> 86124 | G32: =78940+88709 -> 167649 | H32: =G32*(1+I32) -> 171001.98 | I32: 0.02
D33: 70651000 LOYERS LOGEMENTS + ASSOC. | H33: =G33*(1+I33) -> 0 | I33: 0.02
D34: 70880000 REFACT. CH. - CRECHES | F34: =13232+4160 -> 17392 | G34: =4891+13069 -> 17960 | H34: =G34*(1+I34) -> 18319.2 | I34: 0.02
D35: 70881000 REFACT. CH- LOGEMENTS + ASSO | H35: =G35*(1+I35) -> 0 | I35: 0.02
D36: AUTRES PRODUITS | E36: =E37 -> 0 | F36: =F37 -> 0 | G36: =G37 -> 0 | H36: =H37 -> 0
D37: 75800000 PRODUITS DE GESTION COURANTE | E37: 0 | G37: 0
D38: Total des Produits d'exploitation | E38: =E37+E31 -> 0 | F38: =F37+F31 -> 103516 | G38: =G37+G31 -> 185609 | H38: =H37+H31 -> 189321.18
D39: AUTRES ACHATS ET CHARGES EXTERNES | E39: =SUM(E40:E54) -> 108780 | F39: =SUM(F40:F54) -> 29714 | G39: =SUM(G40:G54) -> 14565 | H39: =SUM(H40:H54) -> 14683.92
D40: 60611000 EDF | I40: 0.02
D41: 60612000 EAU | I41: 0.02
D42: 60613000 GAZ | I42: 0.02
D43: 60630000 PETITS OUTILLAGES | I43: 0.02
D44: 61420000 CHARGES LOCATIVES - LOG.+ ASSO | E44: 2226 | F44: =12560+5822 -> 18382 | G44: =1263+7096 -> 8359 | H44: =G44*(1+I44) -> 8526.18 | I44: 0.02
D45: 61510000 ENTRETIEN ET REPARATION CRECHE | G45: 215 | H45: =G45*(1+I45) -> 219.3 | I45: 0.02
D46: 61520000 ENTRETIEN ET REPARATION LOG+AS | I46: 0.02
D47: 61600000 ASSURANCE LOYERS - LOG.+ ASSO. | E47: 868 | F47: 1144 | G47: 1261 | H47: =G47*(1+I47) -> 1286.22 | I47: 0.02
D48: 61600300 ASSURANCE MULTIRISQUE | I48: 0.02
D49: 62260000 HONORAIRES COMPTABLES | E49: 1836 | F49: 1571 | G49: 1557 | H49: =G49*(1+I49) -> 1588.14 | I49: 0.02
D50: 62262000 HONORAIRES JURIDIQUES | E50: 1236 | F50: 327 | G50: 331 | H50: =G50*(1+I50) -> 337.62 | I50: 0.02
D51: 62268000 HONORAIRES DIVERS | E51: 55845 | F51: 7260 | G51: 1861 | H51: =G51*(1+I51) -> 1898.22 | I51: 0.02
D52: 62268200 HONORAIRES GESTION - LOG.+ASS | H52: =G52*(1+I52) -> 0 | I52: 0.02
D53: 62270000 FRAIS D'ACTES ET CONTENCIEUX | E53: 46364 | F53: -20 | I53: 0.02
D54: 62780000 FRAIS BANCAIRES | E54: 405 | F54: 1050 | G54: 981 | H54: =AVERAGE(E54:G54)*(1+I54) -> 828.24 | I54: 0.02
D55: IMPOTS, TAXES ET VERSEMENTS ASSIMILES | E55: =E56+E57 -> 0 | F55: =F56+F57 -> 9740 | G55: =G56+G57 -> 9386 | H55: =H56+H57 -> 9573.72
D56: 63512000 TAXE FONCIERES | F56: 9740 | G56: 9386 | H56: =G56*(1+I56) -> 9573.72 | I56: 0.02
D57: 63513000 TAXE ORDURES MENAGERES | H57: =G57*(1+I57) -> 0
D58: DOTATIONS AUX AMORTISSEMENTS SUR IMMOBILISATIONS | E58: =E59 -> 0 | F58: =F59 -> 49588 | G58: =G59 -> 49588 | H58: =H59 -> 49588
D59: 68112000 DOTATION AMORT. IMMOB.CORP. | F59: 49588 | G59: 49588 | H59: =G59 -> 49588
D60: AUTRES CHARGES | E60: =E61 -> 0 | F60: =F61 -> 0 | G60: =G61 -> 0 | H60: =H61 -> 0
D61: 65800000 CHARGES DE GESTION COURANTE
D62: Total des Charges d'exploitation | E62: =E60+E58+E55+E39 -> 108780 | F62: =F60+F58+F55+F39 -> 89042 | G62: =G60+G58+G55+G39 -> 73539 | H62: =H60+H58+H55+H39 -> 73845.64
D63: Résultat d'exploitation | E63: =E38-E62 -> -108780 | F63: =F38-F62 -> 14474 | G63: =G38-G62 -> 112070 | H63: =H38-H62 -> 115475.54
D64: INTERETS ET CHARGES ASSIMILEES | E64: =E65+E66 -> 23621 | F64: =F65+F66 -> 71781 | G64: =G65+G66 -> 69656 | H64: =H65+H66 -> 65794.739
D65: 66100000 INTERETS BANCAIRES | F65: 47
D66: 66112000 INTERETS DES EMPRUNTS - CE | E66: =7308+16313 -> 23621 | F66: =38045+33689 -> 71734 | G66: 69656 | H66: =-Emprunts!BH15-Emprunts!BH19 -> 65794.739
D67: Total des Charges financières | E67: =E64 -> 23621 | F67: =F64 -> 71781 | G67: =G64 -> 69656 | H67: =H64 -> 65794.739
D68: Résultat financier | E68: =E67 -> 23621 | F68: =F67 -> 71781 | G68: =G67 -> 69656 | H68: =H67 -> 65794.739
D69: Résultat courant avant impôts | E69: =E63-E68 -> -132401 | F69: =F63-F68 -> -57307 | G69: =G63-G68 -> 42414 | H69: =H63-H68 -> 49680.801
D70: 69500000 IS
D71: Résultat NET | E71: =E69-E70 -> -132401 | F71: =F69-F70 -> -57307 | G71: =G69-G70 -> 42414 | H71: =H69-H70 -> 49680.801
D73: IMMOBILISATIONS VO | E73: =SUM(E74:E84) -> 0 | F73: =SUM(F74:F84) -> 1574000 | G73: =SUM(G74:G84) -> 1574000 | H73: =SUM(H74:H84) -> 0
D74: TERRAIN | F74: 472200 | G74: 472200
D75: AGENCEMENTS TERRAIN
D76: GROS ŒUVRE CRECHE | F76: 550900 | G76: 550900
D77: GROS ŒUVRE LOGEMENTS
D78: FACADE ETANCHEITE CRECHE | F78: 275450 | G78: 275450
D79: FACADE ETANCHEITE LOGEMENTS
D80: INSTALLATIONS CRECHE | F80: 165270 | G80: 165270
D81: INSTALLATIONS LOGEMENTS
D82: AGENCEMENTS CRECHE | F82: 110180 | G82: 110180
D83: AGENCEMENTS LOGEMENTS
D84: AGENCEMENTS SUPPL LOGEMENTS
D86: FINANCEMENTS IMMO | E86: =SUM(E87:E92) -> 0 | F86: =SUM(F87:F92) -> 1574000 | G86: =SUM(G87:G92) -> 1574000 | H86: =SUM(H87:H92) -> 0
D87: =D96 -> EMPRUNT LCL 734k€ | F87: 734000 | G87: 734000
D88: =D97 -> EMPRUNT SG 840 k€ | F88: 840000 | G88: 840000
D89: C/C GROUPE
D90: C/C HIO SARLU
D91: C/C AXORIEL SARLU
D92: DETTE FRS
B95: Année fin | C95: Taux | D95: DETTES RESTANTES | E95: =SUM(E96:E107) -> 1574000 | F95: =SUM(F96:F107) -> 1621282 | G95: =SUM(G96:G107) -> 1520154 | H95: =SUM(H96:H107) -> 0
B96: 2038 | C96: 0.046 | D96: EMPRUNT LCL 734k€ | E96: 734000 | F96: 724591 | G96: 685859
B97: 2038 | C97: 0.0453 | D97: EMPRUNT SG 840 k€ | E97: 840000 | F97: 836410 | G97: 792257
D98: Emprunt
D99: DG LOGEMENTS
D100: DG CRECHE | F100: 41197 | G100: 42038
D101: C/C GROUPE
D102: C/C HIO SARLU | F102: 2526
D103: C/C AXORIEL SARLU
D104: CLIENTS AV ET ACPTES RECUS
D105: DETTES FRS | F105: 9132
D106: DETTES FISCALES ET SOCIALES
D107: AUTRES DETTES | F107: 7426
D109: VALORISATION DES BIENS | E109: =SUM(E110:E119) -> 0 | F109: =SUM(F110:F119) -> 0 | G109: =SUM(G110:G119) -> 0 | H109: =SUM(H110:H119) -> 0
D110: ESTIMATION A LA VALEUR DU MARCHE
...

Sheet SCI TAVERNY
A1: SCI TAVERNY
C4: nb m² | D4: LOCATIONS | E4: 2023 | F4: 2024 | G4: 2025 | H4: 2026
D5: =BDD!G16 -> Crèche Taverny | H5: =BDD!S16 -> 67000
D6: Location 2
D7: Location 3
D8: Location 4
D9: Location 5
D10: Location 6
D11: Location 7
D12: Location 8
D13: Location 9
D14: Location 10
D16: CHARGES LOCATIVES | E16: 2023 | F16: 2024 | G16: 2025 | H16: 2026
D17: =D5 -> Crèche Taverny
D18: =D6 -> Location 2
D19: =D7 -> Location 3
D20: =D8 -> Location 4
D21: =D9 -> Location 5
D22: =D10 -> Location 6
D23: =D11 -> Location 7
D24: =D12 -> Location 8
D25: =D13 -> Location 9
D26: =D14 -> Location 10
E29: 2023 | F29: 2024 | G29: 2025 | H29: 2026
D31: PRODUCTION VENDUE DE SERVICES (Chiffre d'affaires) | E31: =SUM(E32:E35) -> 0 | F31: =SUM(F32:F35) -> 0 | G31: =SUM(G32:G35) -> 0 | H31: =SUM(H32:H35) -> 67000
D32: 70650000 LOYERS CRECHES | H32: =H5 -> 67000 | I32: 0.02
D33: 70651000 LOYERS LOGEMENTS + ASSOC. | H33: =G33*(1+I33) -> 0 | I33: 0.02
D34: 70880000 REFACT. CH. - CRECHES | H34: =G34*(1+I34) -> 0 | I34: 0.02
D35: 70881000 REFACT. CH- LOGEMENTS + ASSO | H35: =G35*(1+I35) -> 0 | I35: 0.02
D36: AUTRES PRODUITS | E36: =E37 -> 0 | F36: =F37 -> 0 | G36: =G37 -> 0 | H36: =H37 -> 0
D37: 75800000 PRODUITS DE GESTION COURANTE | E37: 0 | G37: 0
D38: Total des Produits d'exploitation | E38: =E37+E31 -> 0 | F38: =F37+F31 -> 0 | G38: =G37+G31 -> 0 | H38: =H37+H31 -> 67000
D39: AUTRES ACHATS ET CHARGES EXTERNES | E39: =SUM(E40:E54) -> 20051 | F39: =SUM(F40:F54) -> 117742 | G39: =SUM(G40:G54) -> 11296 | H39: =SUM(H40:H54) -> 11521.92
D40: 60611000 EDF | I40: 0.02
D41: 60612000 EAU | I41: 0.02
D42: 60613000 GAZ | I42: 0.02
D43: 60630000 PETITS OUTILLAGES | I43: 0.02
D44: 61420000 CHARGES LOCATIVES - LOG.+ ASSO | H44: =G44*(1+I44) -> 0 | I44: 0.02
D45: 61510000 ENTRETIEN ET REPARATION CRECHE | I45: 0.02
D46: 61520000 ENTRETIEN ET REPARATION LOG+AS | I46: 0.02
D47: 61600000 ASSURANCE LOYERS - LOG.+ ASSO. | F47: 4408 | G47: 4607 | H47: =G47*(1+I47) -> 4699.14 | I47: 0.02
D48: 61600300 ASSURANCE MULTIRISQUE | I48: 0.02
D49: 62260000 HONORAIRES COMPTABLES | E49: 1836 | F49: 1123 | G49: 1123 | H49: =G49*(1+I49) -> 1145.46 | I49: 0.02
D50: 62262000 HONORAIRES JURIDIQUES | E50: 1626 | F50: 315 | G50: 322 | H50: =G50*(1+I50) -> 328.44 | I50: 0.02
D51: 62268000 HONORAIRES DIVERS | E51: 7613 | F51: 73062 | G51: 4715 | H51: =G51*(1+I51) -> 4809.3 | I51: 0.02
D52: 62268200 HONORAIRES GESTION - LOG.+ASS | H52: =G52*(1+I52) -> 0 | I52: 0.02
D53: 62270000 FRAIS D'ACTES ET CONTENCIEUX | E53: 8892 | F53: 35736 | I53: 0.02
D54: 62780000 FRAIS BANCAIRES | E54: 84 | F54: 3098 | G54: 529 | H54: =(G54)*(1+I54) -> 539.58 | I54: 0.02
D55: IMPOTS, TAXES ET VERSEMENTS ASSIMILES | E55: =E56+E57 -> 0 | F55: =F56+F57 -> 0 | G55: =G56+G57 -> 0 | H55: =H56+H57 -> 0
D56: 63512000 TAXE FONCIERES | H56: =G56*(1+I56) -> 0 | I56: 0.02
D57: 63513000 TAXE ORDURES MENAGERES | H57: =G57*(1+I57) -> 0
D58: DOTATIONS AUX AMORTISSEMENTS SUR IMMOBILISATIONS | E58: =E59 -> 0 | F58: =F59 -> 0 | G58: =G59 -> 0 | H58: =H59 -> 47000
D59: 68112000 DOTATION AMORT. IMMOB.CORP. | H59: =H74/20 -> 47000
D60: AUTRES CHARGES | E60: =E61 -> 0 | F60: =F61 -> 0 | G60: =G61 -> 0 | H60: =H61 -> 0
D61: 65800000 CHARGES DE GESTION COURANTE
D62: Total des Charges d'exploitation | E62: =E60+E58+E55+E39 -> 20051 | F62: =F60+F58+F55+F39 -> 117742 | G62: =G60+G58+G55+G39 -> 11296 | H62: =H60+H58+H55+H39 -> 58521.92
D63: Résultat d'exploitation | E63: =E38-E62 -> -20051 | F63: =F38-F62 -> -117742 | G63: =G38-G62 -> -11296 | H63: =H38-H62 -> 8478.08
D64: INTERETS ET CHARGES ASSIMILEES | E64: =E65+E66 -> 0 | F64: =F65+F66 -> 32834 | G64: =G65+G66 -> 47743 | H64: =H65+H66 -> 65864.577
D65: 66100000 INTERETS BANCAIRES
D66: 66112000 INTERETS DES EMPRUNTS - CE | F66: 32834 | G66: 47743 | H66: =-Emprunts!BH16 -> 65864.577
D67: Total des Charges financières | E67: =E64 -> 0 | F67: =F64 -> 32834 | G67: =G64 -> 47743 | H67: =H64 -> 65864.577
D68: Résultat financier | E68: =E67 -> 0 | F68: =F67 -> 32834 | G68: =G67 -> 47743 | H68: =H67 -> 65864.577
D69: Résultat courant avant impôts | E69: =E63-E68 -> -20051 | F69: =F63-F68 -> -150576 | G69: =G63-G68 -> -59039 | H69: =H63-H68 -> -57386.497
D70: 69500000 IS
D71: Résultat NET | E71: =E69-E70 -> -20051 | F71: =F69-F70 -> -150576 | G71: =G69-G70 -> -59039 | H71: =H69-H70 -> -57386.497
D73: IMMOBILISATIONS VO | E73: =SUM(E74:E85) -> 0 | F73: =SUM(F74:F85) -> 869525 | G73: =SUM(G74:G85) -> 869525 | H73: =SUM(H74:H85) -> 940000
D74: IMMO CORPORELLES EN COURS | F74: 869525 | G74: 869525 | H74: 940000
D75: TERRAIN
D76: AGENCEMENTS TERRAIN
D77: GROS ŒUVRE CRECHE
D78: GROS ŒUVRE LOGEMENTS
D79: FACADE ETANCHEITE CRECHE
D80: FACADE ETANCHEITE LOGEMENTS
D81: INSTALLATIONS CRECHE
D82: INSTALLATIONS LOGEMENTS
D83: AGENCEMENTS CRECHE
D84: AGENCEMENTS LOGEMENTS
D85: AGENCEMENTS SUPPL LOGEMENTS
D87: FINANCEMENTS IMMO | E87: =SUM(E88:E93) -> 1408923 | F87: =SUM(F88:F93) -> 1408923 | G87: =G81-G82 -> 0 | H87: =H81-H82 -> 0
D88: =D97 -> EMPRUNT CE 1408k€ | E88: 1408923 | F88: 1408923 | G88: 1408923
D89: =D98 -> Emprunt
D90: C/C GROUPE
D91: C/C HIO SARLU
D92: C/C AXORIEL SARLU
D93: DETTE FRS
B96: Année fin | C96: Taux | D96: DETTES RESTANTES | E96: =SUM(E97:E108) -> 509847 | F96: =SUM(F97:F108) -> 1015216 | G96: =SUM(G97:G108) -> 940717 | H96: =SUM(H97:H108) -> 0
B97: 2043 | C97: 0.0493 | D97: EMPRUNT CE 1408k€ | E97: 472512 | F97: 940717 | G97: 940717
D98: Emprunt
D99: Emprunt
D100: DG LOGEMENTS
D101: DG CRECHE
D102: C/C GROUPE | E102: 750 | F102: 750
D103: C/C HIO SARLU | F103: 18978
D104: C/C AXORIEL SARLU | E104: 25510 | F104: 43487
D105: CLIENTS AV ET ACPTES RECUS
D106: DETTES FRS | E106: 11075 | F106: 8043
D107: DETTES FISCALES ET SOCIALES
D108: AUTRES DETTES | F108: 3241
D110: VALORISATION DES BIENS | E110: =SUM(E111:E120) -> 0 | F110: =SUM(F111:F120) -> 0 | G110: =SUM(G111:G120) -> 0 | H110: =SUM(H111:H120) -> 0
D111: ESTIMATION A LA VALEUR DU MARCHE
...

Sheet SCI GENERAL JULES BRIMONT
A1: SCI GENERAL JULES BRIMONT
C4: nb m² | D4: LOCATIONS | E4: 2023 | F4: 2024 | G4: 2025 | H4: 2026
D5: =BDD!G17 -> Crèche Chatou | H5: =BDD!S17 -> 84000
D6: =BDD!G18 -> Bureau au RDC | H6: =BDD!S18 -> 10865.28
D7: =BDD!G19 -> Local professionnel | H7: =BDD!S19 -> 3185
D8: =BDD!G20 -> Local professionnel | H8: =BDD!S20 -> 11788.32
D9: =BDD!G21 -> Bureau au RDC | H9: =BDD!S21 -> 7084
D10: =BDD!G22 -> Bureau au RDC | H10: =BDD!S22 -> 8040.24
D11: =BDD!G23 -> Crèche LPB | H11: =BDD!S23 -> 80000
D12: Location 8
D13: Location 9
D14: Location 10
D16: CHARGES LOCATIVES | E16: 2023 | F16: 2024 | G16: 2025 | H16: 2026
D17: =D5 -> Crèche Chatou
D18: =D6 -> Bureau au RDC
D19: =D7 -> Local professionnel
D20: =D8 -> Local professionnel
D21: =D9 -> Bureau au RDC
D22: =D10 -> Bureau au RDC
D23: =D11 -> Crèche LPB
D24: =D12 -> Location 8
D25: =D13 -> Location 9
D26: =D14 -> Location 10
E29: 2023 | F29: 2024 | G29: 2025 | H29: 2026
D31: PRODUCTION VENDUE DE SERVICES (Chiffre d'affaires) | E31: =SUM(E32:E35) -> 4984 | F31: =SUM(F32:F35) -> 73888 | G31: =SUM(G32:G35) -> 229252 | H31: =SUM(H32:H35) -> 244653.98
D32: 70650000 LOYERS CRECHES | F32: =29127+26522 -> 55649 | G32: 170486 | H32: =G32*(1+I32) -> 173895.72 | I32: 0.02
D33: 70651000 LOYERS LOGEMENTS + ASSOC. | E33: 3534 | F33: 8049 | G33: =200844-G32 -> 30358 | H33: =SUM(H6:H10)*(1+I33) -> 41782.097 | I33: 0.02
D34: 70880000 REFACT. CH. - CRECHES | F34: =5752+2828 -> 8580 | G34: 24467 | H34: =G34*(1+I34) -> 24956.34 | I34: 0.02
D35: 70881000 REFACT. CH- LOGEMENTS + ASSO | E35: 1450 | F35: 1610 | G35: =28408-G34 -> 3941 | H35: =G35*(1+I35) -> 4019.82 | I35: 0.02
D36: AUTRES PRODUITS | E36: =E37 -> 0 | F36: =F37 -> 0 | G36: =G37 -> 0 | H36: =H37 -> 0
D37: 75800000 PRODUITS DE GESTION COURANTE | E37: 0 | G37: 0
D38: Total des Produits d'exploitation | E38: =E37+E31 -> 4984 | F38: =F37+F31 -> 73888 | G38: =G37+G31 -> 229252 | H38: =H37+H31 -> 244653.98
D39: AUTRES ACHATS ET CHARGES EXTERNES | E39: =SUM(E40:E54) -> 189144 | F39: =SUM(F40:F54) -> 34964 | G39: =SUM(G40:G54) -> 36411 | H39: =SUM(H40:H54) -> 37057.62
D40: 60611000 EDF | I40: 0.02
D41: 60612000 EAU | I41: 0.02
D42: 60613000 GAZ | I42: 0.02
D43: 60630000 PETITS OUTILLAGES | G43: 80 | I43: 0.02
D44: 61420000 CHARGES LOCATIVES - LOG.+ ASSO | E44: 5113 | F44: 8277 | G44: 9497 | H44: =G44*(1+I44) -> 9686.94 | I44: 0.02
D45: 61510000 ENTRETIEN ET REPARATION CRECHE | E45: 1602 | F45: =5942+3380 -> 9322 | G45: 8050 | H45: =G45*(1+I45) -> 8211 | I45: 0.02
D46: 61520000 ENTRETIEN ET REPARATION LOG+AS | I46: 0.02
D47: 61600000 ASSURANCE LOYERS - LOG.+ ASSO. | E47: 356 | F47: 961 | G47: 989 | H47: =G47*(1+I47) -> 1008.78 | I47: 0.02
D48: 61600300 ASSURANCE MULTIRISQUE | I48: 0.02
D49: 62260000 HONORAIRES COMPTABLES | E49: 1836 | F49: 1440 | G49: 1498 | H49: =G49*(1+I49) -> 1527.96 | I49: 0.02
D50: 62262000 HONORAIRES JURIDIQUES | E50: 2384 | F50: 306 | G50: 318 | H50: =G50*(1+I50) -> 324.36 | I50: 0.02
D51: 62268000 HONORAIRES DIVERS | E51: 13118 | F51: 12989 | G51: 14613 | H51: =G51*(1+I51) -> 14905.26 | I51: 0.02
D52: 62268200 HONORAIRES GESTION - LOG.+ASS | H52: =G52*(1+I52) -> 0 | I52: 0.02
D53: 62270000 FRAIS D'ACTES ET CONTENCIEUX | E53: 164592 | F53: 1030 | G53: 420 | H53: =(G53)*(1+I53) -> 428.4 | I53: 0.02
D54: 62780000 FRAIS BANCAIRES | E54: 143 | F54: 639 | G54: 946 | H54: =(G54)*(1+I54) -> 964.92 | I54: 0.02
D55: IMPOTS, TAXES ET VERSEMENTS ASSIMILES | E55: =E56+E57 -> 4684 | F55: =F56+F57 -> 12566 | G55: =G56+G57 -> 17274 | H55: =H56+H57 -> 17619.48
D56: 63512000 TAXE FONCIERES | E56: 4684 | F56: 12566 | G56: 17274 | H56: =G56*(1+I56) -> 17619.48 | I56: 0.02
D57: 63513000 TAXE ORDURES MENAGERES | H57: =G57*(1+I57) -> 0
D58: DOTATIONS AUX AMORTISSEMENTS SUR IMMOBILISATIONS | E58: =E59 -> 16988 | F58: =F59 -> 61118 | G58: =G59 -> 61118 | H58: =H59 -> 61118
D59: 68112000 DOTATION AMORT. IMMOB.CORP. | E59: 16988 | F59: 61118 | G59: =F59 -> 61118 | H59: =F59 -> 61118
D60: AUTRES CHARGES | E60: =E61 -> 0 | F60: =F61 -> 0 | G60: =G61 -> 0 | H60: =H61 -> 0
D61: 65800000 CHARGES DE GESTION COURANTE
D62: Total des Charges d'exploitation | E62: =E60+E58+E55+E39 -> 210816 | F62: =F60+F58+F55+F39 -> 108648 | G62: =G60+G58+G55+G39 -> 114803 | H62: =H60+H58+H55+H39 -> 115795.1
D63: Résultat d'exploitation | E63: =E38-E62 -> -205832 | F63: =F38-F62 -> -34760 | G63: =G38-G62 -> 114449 | H63: =H38-H62 -> 128858.88
D64: INTERETS ET CHARGES ASSIMILEES | E64: =E65+E66 -> 40362 | F64: =F65+F66 -> 93845 | G64: =G65+G66 -> 89429 | H64: =H65+H66 -> 85135.128
D65: 66100000 INTERETS BANCAIRES
D66: 66112000 INTERETS DES EMPRUNTS - CE | E66: 40362 | F66: 93845 | G66: 89429 | H66: =-Emprunts!BH17-Emprunts!BH18 -> 85135.128
D67: Total des Charges financières | E67: =E64 -> 40362 | F67: =F64 -> 93845 | G67: =G64 -> 89429 | H67: =H64 -> 85135.128
D68: Résultat financier | E68: =E67 -> 40362 | F68: =F67 -> 93845 | G68: =G67 -> 89429 | H68: =H67 -> 85135.128
D69: Résultat courant avant impôts | E69: =E63-E68 -> -246194 | F69: =F63-F68 -> -128605 | G69: =G63-G68 -> 25020 | H69: =H63-H68 -> 43723.749
D70: 69500000 IS
D71: Résultat NET | E71: =E69-E70 -> -246194 | F71: =F69-F70 -> -128605 | G71: =G69-G70 -> 25020 | H71: =H69-H70 -> 43723.749
D73: IMMOBILISATIONS VO | E73: =SUM(E74:E84) -> 1200000 | F73: =SUM(F74:F84) -> 2002676 | G73: =SUM(G74:G84) -> 2002676 | H73: =SUM(H74:H84) -> 0
D74: TERRAIN | E74: 360000 | F74: 582000 | G74: 582000
D75: AGENCEMENTS TERRAIN
D76: GROS ŒUVRE CRECHE | E76: 420000 | F76: 679000 | G76: 679000
D77: GROS ŒUVRE LOGEMENTS
D78: FACADE ETANCHEITE CRECHE | E78: 210000 | F78: 339500 | G78: 339500
D79: FACADE ETANCHEITE LOGEMENTS
D80: INSTALLATIONS CRECHE | E80: 126000 | F80: 203700 | G80: 203700
D81: INSTALLATIONS LOGEMENTS
D82: AGENCEMENTS CRECHE | E82: 84000 | F82: 135800 | G82: 135800
D83: AGENCEMENTS LOGEMENTS
D84: AGENCEMENTS SUPPL LOGEMENTS | F84: 62676 | G84: 62676
D86: FINANCEMENTS IMMO | E86: =SUM(E87:E92) -> 2132925 | F86: =SUM(F87:F92) -> 2039279 | G86: =SUM(G87:G92) -> 1940000 | H86: =H80-H81 -> 0
D87: =D96 -> EMPRUNT CE 1200k€ | E87: 1200000 | F87: 1200000 | G87: 1200000
D88: =D97 -> EMPRUNT LCL 740k€ | E88: 740000 | F88: 740000 | G88: 740000
D89: C/C GROUPE
D90: C/C HIO SARLU | E90: =E102 -> 76751 | F90: =F102 -> 45678
D91: C/C AXORIEL SARLU | E91: =E103 -> 116174 | F91: =F103 -> 53601
D92: DETTE FRS
B95: Année fin | C95: Taux | D95: DETTES RESTANTES | E95: =SUM(E96:E107) -> 2192479 | F95: =SUM(F96:F107) -> 2046752 | G95: =SUM(G96:G107) -> 1823796 | H95: =SUM(H96:H107) -> 0
B96: 2039 | C96: 0.051 | D96: EMPRUNT CE 1200k€ | E96: 1200000 | F96: 1149972 | G96: 1092668
B97: 2039 | C97: 0.046 | D97: EMPRUNT LCL 740k€ | E97: 740000 | F97: 721809 | G97: 684153
D98: Emprunt
D99: DG LOGEMENTS | E99: 23811 | F99: 46007 | G99: 46975
D100: DG CRECHE
D101: C/C GROUPE | E101: 750 | F101: 750
D102: C/C HIO SARLU | E102: 76751 | F102: 45678
D103: C/C AXORIEL SARLU | E103: 116174 | F103: 53601
D104: CLIENTS AV ET ACPTES RECUS
D105: DETTES FRS | E105: 26051 | F105: 20230
D106: DETTES FISCALES ET SOCIALES
D107: AUTRES DETTES | E107: 8942 | F107: 8705
D109: VALORISATION DES BIENS | E109: =SUM(E110:E119) -> 0 | F109: =SUM(F110:F119) -> 0 | G109: =SUM(G110:G119) -> 0 | H109: =SUM(H110:H119) -> 0
D110: ESTIMATION A LA VALEUR DU MARCHE
D111: =D5 -> Crèche Chatou | E111: 0 | F111: 0 | G111: 0
...

Sheet CONSO
A1: SCI 34 RUE HAUTE
C4: nb m² | D4: LOCATIONS | E4: 2023 | F4: 2024 | G4: 2025 | H4: 2026
D5: =BDD!D4&" "&BDD!G4 -> DEUIL LA BARRE Crèche
D6: =BDD!D5&" "&BDD!G5 -> DEUIL LA BARRE Ecole
D7: =BDD!D6&" "&BDD!G6 -> DEUIL LA BARRE Logements 1 appartement avec terrasse et jardin RDC
D8: =BDD!D7&" "&BDD!G7 -> DEUIL LA BARRE Logements 2 appartement RDC
D9: =BDD!D8&" "&BDD!G8 -> DEUIL LA BARRE Logements 3 1er étage à droite
D10: =BDD!D9&" "&BDD!G9 -> DEUIL LA BARRE Logements 4 1er étage à gauche
D11: Location 7
D12: Location 8
D13: Location 9
D14: Location 10
D16: CHARGES LOCATIVES | E16: 2023 | F16: 2024 | G16: 2025 | H16: 2026
D17: =D5 -> DEUIL LA BARRE Crèche
D18: =D6 -> DEUIL LA BARRE Ecole
D19: =D7 -> DEUIL LA BARRE Logements 1 appartement avec terrasse et jardin RDC
D20: =D8 -> DEUIL LA BARRE Logements 2 appartement RDC
D21: =D9 -> DEUIL LA BARRE Logements 3 1er étage à droite
D22: =D10 -> DEUIL LA BARRE Logements 4 1er étage à gauche
D23: =D11 -> Location 7
D24: =D12 -> Location 8
D25: =D13 -> Location 9
D26: =D14 -> Location 10
E29: 2023 | F29: 2024 | G29: 2025 | H29: 2026
D31: PRODUCTION VENDUE DE SERVICES (Chiffre d'affaires) | E31: =SUM(E32:E35) -> 384377 | F31: =SUM(F32:F35) -> 652375 | G31: =SUM(G32:G35) -> 907670 | H31: =SUM(H32:H35) -> 1003640.3
D32: 70650000 LOYERS CRECHES | E32: ='SCI 34 RUE HAUTE'!E32+'SCI LEGRAND'!E32+'SCI ARMEE ORIENT'!E32+'SCI CHENNEVIERES'!E32+'SCI TAVERNY'!E32+'SCI GENERAL JULES BRIMONT'!E32 -> 311210 | F32: ='SCI 34 RUE HAUTE'!F32+'SCI LEGRAND'!F32+'SCI ARMEE ORIENT'!F32+'SCI CHENNEVIERES'!F32+'SCI TAVERNY'!F32+'SCI GENERAL JULES BRIMONT'!F32 -> 461933 | G32: ='SCI 34 RUE HAUTE'!G32+'SCI LEGRAND'!G32+'SCI ARMEE ORIENT'!G32+'SCI CHENNEVIERES'!G32+'SCI TAVERNY'!G32+'SCI GENERAL JULES BRIMONT'!G32 -> 668092 | H32: ='SCI 34 RUE HAUTE'!H32+'SCI LEGRAND'!H32+'SCI ARMEE ORIENT'!H32+'SCI CHENNEVIERES'!H32+'SCI TAVERNY'!H32+'SCI GENERAL JULES BRIMONT'!H32 -> 748453.84
D33: 70651000 LOYERS LOGEMENTS + ASSOC. | E33: ='SCI 34 RUE HAUTE'!E33+'SCI LEGRAND'!E33+'SCI ARMEE ORIENT'!E33+'SCI CHENNEVIERES'!E33+'SCI TAVERNY'!E33+'SCI GENERAL JULES BRIMONT'!E33 -> 7232 | F33: ='SCI 34 RUE HAUTE'!F33+'SCI LEGRAND'!F33+'SCI ARMEE ORIENT'!F33+'SCI CHENNEVIERES'!F33+'SCI TAVERNY'!F33+'SCI GENERAL JULES BRIMONT'!F33 -> 71477 | G33: ='SCI 34 RUE HAUTE'!G33+'SCI LEGRAND'!G33+'SCI ARMEE ORIENT'!G33+'SCI CHENNEVIERES'!G33+'SCI TAVERNY'!G33+'SCI GENERAL JULES BRIMONT'!G33 -> 106985 | H33: ='SCI 34 RUE HAUTE'!H33+'SCI LEGRAND'!H33+'SCI ARMEE ORIENT'!H33+'SCI CHENNEVIERES'!H33+'SCI TAVERNY'!H33+'SCI GENERAL JULES BRIMONT'!H33 -> 119941.64
D34: 70880000 REFACT. CH. - CRECHES | E34: ='SCI 34 RUE HAUTE'!E34+'SCI LEGRAND'!E34+'SCI ARMEE ORIENT'!E34+'SCI CHENNEVIERES'!E34+'SCI TAVERNY'!E34+'SCI GENERAL JULES BRIMONT'!E34 -> 64112 | F34: ='SCI 34 RUE HAUTE'!F34+'SCI LEGRAND'!F34+'SCI ARMEE ORIENT'!F34+'SCI CHENNEVIERES'!F34+'SCI TAVERNY'!F34+'SCI GENERAL JULES BRIMONT'!F34 -> 110856 | G34: ='SCI 34 RUE HAUTE'!G34+'SCI LEGRAND'!G34+'SCI ARMEE ORIENT'!G34+'SCI CHENNEVIERES'!G34+'SCI TAVERNY'!G34+'SCI GENERAL JULES BRIMONT'!G34 -> 119779 | H34: ='SCI 34 RUE HAUTE'!H34+'SCI LEGRAND'!H34+'SCI ARMEE ORIENT'!H34+'SCI CHENNEVIERES'!H34+'SCI TAVERNY'!H34+'SCI GENERAL JULES BRIMONT'!H34 -> 122174.58
D35: 70881000 REFACT. CH- LOGEMENTS + ASSO | E35: ='SCI 34 RUE HAUTE'!E35+'SCI LEGRAND'!E35+'SCI ARMEE ORIENT'!E35+'SCI CHENNEVIERES'!E35+'SCI TAVERNY'!E35+'SCI GENERAL JULES BRIMONT'!E35 -> 1823 | F35: ='SCI 34 RUE HAUTE'!F35+'SCI LEGRAND'!F35+'SCI ARMEE ORIENT'!F35+'SCI CHENNEVIERES'!F35+'SCI TAVERNY'!F35+'SCI GENERAL JULES BRIMONT'!F35 -> 8109 | G35: ='SCI 34 RUE HAUTE'!G35+'SCI LEGRAND'!G35+'SCI ARMEE ORIENT'!G35+'SCI CHENNEVIERES'!G35+'SCI TAVERNY'!G35+'SCI GENERAL JULES BRIMONT'!G35 -> 12814 | H35: ='SCI 34 RUE HAUTE'!H35+'SCI LEGRAND'!H35+'SCI ARMEE ORIENT'!H35+'SCI CHENNEVIERES'!H35+'SCI TAVERNY'!H35+'SCI GENERAL JULES BRIMONT'!H35 -> 13070.28
D36: AUTRES PRODUITS | E36: =E37 -> 0 | F36: =F37 -> 174 | G36: =G37 -> 4081 | H36: =H37 -> 0
D37: 75800000 PRODUITS DE GESTION COURANTE | E37: ='SCI 34 RUE HAUTE'!E37+'SCI LEGRAND'!E37+'SCI ARMEE ORIENT'!E37+'SCI CHENNEVIERES'!E37+'SCI TAVERNY'!E37+'SCI GENERAL JULES BRIMONT'!E37 -> 0 | F37: ='SCI 34 RUE HAUTE'!F37+'SCI LEGRAND'!F37+'SCI ARMEE ORIENT'!F37+'SCI CHENNEVIERES'!F37+'SCI TAVERNY'!F37+'SCI GENERAL JULES BRIMONT'!F37 -> 174 | G37: ='SCI 34 RUE HAUTE'!G37+'SCI LEGRAND'!G37+'SCI ARMEE ORIENT'!G37+'SCI CHENNEVIERES'!G37+'SCI TAVERNY'!G37+'SCI GENERAL JULES BRIMONT'!G37 -> 4081 | H37: ='SCI 34 RUE HAUTE'!H37+'SCI LEGRAND'!H37+'SCI ARMEE ORIENT'!H37+'SCI CHENNEVIERES'!H37+'SCI TAVERNY'!H37+'SCI GENERAL JULES BRIMONT'!H37 -> 0
D38: Total des Produits d'exploitation | E38: =E37+E31 -> 384377 | F38: =F37+F31 -> 652549 | G38: =G37+G31 -> 911751 | H38: =H37+H31 -> 1003640.3
D39: AUTRES ACHATS ET CHARGES EXTERNES | E39: =SUM(E40:E54) -> 416764 | F39: =SUM(F40:F54) -> 263673 | G39: =SUM(G40:G54) -> 150407.07 | H39: =SUM(H40:H54) -> 153015.18
D40: 60611000 EDF | E40: ='SCI 34 RUE HAUTE'!E40+'SCI LEGRAND'!E40+'SCI ARMEE ORIENT'!E40+'SCI CHENNEVIERES'!E40+'SCI TAVERNY'!E40+'SCI GENERAL JULES BRIMONT'!E40 -> 1976 | F40: ='SCI 34 RUE HAUTE'!F40+'SCI LEGRAND'!F40+'SCI ARMEE ORIENT'!F40+'SCI CHENNEVIERES'!F40+'SCI TAVERNY'!F40+'SCI GENERAL JULES BRIMONT'!F40 -> 3206 | G40: ='SCI 34 RUE HAUTE'!G40+'SCI LEGRAND'!G40+'SCI ARMEE ORIENT'!G40+'SCI CHENNEVIERES'!G40+'SCI TAVERNY'!G40+'SCI GENERAL JULES BRIMONT'!G40 -> 1860.2 | H40: ='SCI 34 RUE HAUTE'!H40+'SCI LEGRAND'!H40+'SCI ARMEE ORIENT'!H40+'SCI CHENNEVIERES'!H40+'SCI TAVERNY'!H40+'SCI GENERAL JULES BRIMONT'!H40 -> 2394.348
D41: 60612000 EAU | E41: ='SCI 34 RUE HAUTE'!E41+'SCI LEGRAND'!E41+'SCI ARMEE ORIENT'!E41+'SCI CHENNEVIERES'!E41+'SCI TAVERNY'!E41+'SCI GENERAL JULES BRIMONT'!E41 -> 2562 | F41: ='SCI 34 RUE HAUTE'!F41+'SCI LEGRAND'!F41+'SCI ARMEE ORIENT'!F41+'SCI CHENNEVIERES'!F41+'SCI TAVERNY'!F41+'SCI GENERAL JULES BRIMONT'!F41 -> 3339 | G41: ='SCI 34 RUE HAUTE'!G41+'SCI LEGRAND'!G41+'SCI ARMEE ORIENT'!G41+'SCI CHENNEVIERES'!G41+'SCI TAVERNY'!G41+'SCI GENERAL JULES BRIMONT'!G41 -> 3387 | H41: ='SCI 34 RUE HAUTE'!H41+'SCI LEGRAND'!H41+'SCI ARMEE ORIENT'!H41+'SCI CHENNEVIERES'!H41+'SCI TAVERNY'!H41+'SCI GENERAL JULES BRIMONT'!H41 -> 3157.92
D42: 60613000 GAZ | E42: ='SCI 34 RUE HAUTE'!E42+'SCI LEGRAND'!E42+'SCI ARMEE ORIENT'!E42+'SCI CHENNEVIERES'!E42+'SCI TAVERNY'!E42+'SCI GENERAL JULES BRIMONT'!E42 -> 894 | F42: ='SCI 34 RUE HAUTE'!F42+'SCI LEGRAND'!F42+'SCI ARMEE ORIENT'!F42+'SCI CHENNEVIERES'!F42+'SCI TAVERNY'!F42+'SCI GENERAL JULES BRIMONT'!F42 -> 328 | G42: ='SCI 34 RUE HAUTE'!G42+'SCI LEGRAND'!G42+'SCI ARMEE ORIENT'!G42+'SCI CHENNEVIERES'!G42+'SCI TAVERNY'!G42+'SCI GENERAL JULES BRIMONT'!G42 -> 0 | H42: ='SCI 34 RUE HAUTE'!H42+'SCI LEGRAND'!H42+'SCI ARMEE ORIENT'!H42+'SCI CHENNEVIERES'!H42+'SCI TAVERNY'!H42+'SCI GENERAL JULES BRIMONT'!H42 -> 623.22
D43: 60630000 PETITS OUTILLAGES | E43: ='SCI 34 RUE HAUTE'!E43+'SCI LEGRAND'!E43+'SCI ARMEE ORIENT'!E43+'SCI CHENNEVIERES'!E43+'SCI TAVERNY'!E43+'SCI GENERAL JULES BRIMONT'!E43 -> 1510 | F43: ='SCI 34 RUE HAUTE'!F43+'SCI LEGRAND'!F43+'SCI ARMEE ORIENT'!F43+'SCI CHENNEVIERES'!F43+'SCI TAVERNY'!F43+'SCI GENERAL JULES BRIMONT'!F43 -> 0 | G43: ='SCI 34 RUE HAUTE'!G43+'SCI LEGRAND'!G43+'SCI ARMEE ORIENT'!G43+'SCI CHENNEVIERES'!G43+'SCI TAVERNY'!G43+'SCI GENERAL JULES BRIMONT'!G43 -> 80 | H43: ='SCI 34 RUE HAUTE'!H43+'SCI LEGRAND'!H43+'SCI ARMEE ORIENT'!H43+'SCI CHENNEVIERES'!H43+'SCI TAVERNY'!H43+'SCI GENERAL JULES BRIMONT'!H43 -> 770.1
D44: 61420000 CHARGES LOCATIVES - LOG.+ ASSO | E44: ='SCI 34 RUE HAUTE'!E44+'SCI LEGRAND'!E44+'SCI ARMEE ORIENT'!E44+'SCI CHENNEVIERES'!E44+'SCI TAVERNY'!E44+'SCI GENERAL JULES BRIMONT'!E44 -> 49318 | F44: ='SCI 34 RUE HAUTE'!F44+'SCI LEGRAND'!F44+'SCI ARMEE ORIENT'!F44+'SCI CHENNEVIERES'!F44+'SCI TAVERNY'!F44+'SCI GENERAL JULES BRIMONT'!F44 -> 69204 | G44: ='SCI 34 RUE HAUTE'!G44+'SCI LEGRAND'!G44+'SCI ARMEE ORIENT'!G44+'SCI CHENNEVIERES'!G44+'SCI TAVERNY'!G44+'SCI GENERAL JULES BRIMONT'!G44 -> 63834 | H44: ='SCI 34 RUE HAUTE'!H44+'SCI LEGRAND'!H44+'SCI ARMEE ORIENT'!H44+'SCI CHENNEVIERES'!H44+'SCI TAVERNY'!H44+'SCI GENERAL JULES BRIMONT'!H44 -> 65110.68
D45: 61510000 ENTRETIEN ET REPARATION CRECHE | E45: ='SCI 34 RUE HAUTE'!E45+'SCI LEGRAND'!E45+'SCI ARMEE ORIENT'!E45+'SCI CHENNEVIERES'!E45+'SCI TAVERNY'!E45+'SCI GENERAL JULES BRIMONT'!E45 -> 8109 | F45: ='SCI 34 RUE HAUTE'!F45+'SCI LEGRAND'!F45+'SCI ARMEE ORIENT'!F45+'SCI CHENNEVIERES'!F45+'SCI TAVERNY'!F45+'SCI GENERAL JULES BRIMONT'!F45 -> 12174 | G45: ='SCI 34 RUE HAUTE'!G45+'SCI LEGRAND'!G45+'SCI ARMEE ORIENT'!G45+'SCI CHENNEVIERES'!G45+'SCI TAVERNY'!G45+'SCI GENERAL JULES BRIMONT'!G45 -> 12867.7 | H45: ='SCI 34 RUE HAUTE'!H45+'SCI LEGRAND'!H45+'SCI ARMEE ORIENT'!H45+'SCI CHENNEVIERES'!H45+'SCI TAVERNY'!H45+'SCI GENERAL JULES BRIMONT'!H45 -> 13756.638
D46: 61520000 ENTRETIEN ET REPARATION LOG+AS | E46: ='SCI 34 RUE HAUTE'!E46+'SCI LEGRAND'!E46+'SCI ARMEE ORIENT'!E46+'SCI CHENNEVIERES'!E46+'SCI TAVERNY'!E46+'SCI GENERAL JULES BRIMONT'!E46 -> 0 | F46: ='SCI 34 RUE HAUTE'!F46+'SCI LEGRAND'!F46+'SCI ARMEE ORIENT'!F46+'SCI CHENNEVIERES'!F46+'SCI TAVERNY'!F46+'SCI GENERAL JULES BRIMONT'!F46 -> 120 | G46: ='SCI 34 RUE HAUTE'!G46+'SCI LEGRAND'!G46+'SCI ARMEE ORIENT'!G46+'SCI CHENNEVIERES'!G46+'SCI TAVERNY'!G46+'SCI GENERAL JULES BRIMONT'!G46 -> 0 | H46: ='SCI 34 RUE HAUTE'!H46+'SCI LEGRAND'!H46+'SCI ARMEE ORIENT'!H46+'SCI CHENNEVIERES'!H46+'SCI TAVERNY'!H46+'SCI GENERAL JULES BRIMONT'!H46 -> 122.4
D47: 61600000 ASSURANCE LOYERS - LOG.+ ASSO. | E47: ='SCI 34 RUE HAUTE'!E47+'SCI LEGRAND'!E47+'SCI ARMEE ORIENT'!E47+'SCI CHENNEVIERES'!E47+'SCI TAVERNY'!E47+'SCI GENERAL JULES BRIMONT'!E47 -> 2479 | F47: ='SCI 34 RUE HAUTE'!F47+'SCI LEGRAND'!F47+'SCI ARMEE ORIENT'!F47+'SCI CHENNEVIERES'!F47+'SCI TAVERNY'!F47+'SCI GENERAL JULES BRIMONT'!F47 -> 8636 | G47: ='SCI 34 RUE HAUTE'!G47+'SCI LEGRAND'!G47+'SCI ARMEE ORIENT'!G47+'SCI CHENNEVIERES'!G47+'SCI TAVERNY'!G47+'SCI GENERAL JULES BRIMONT'!G47 -> 9157 | H47: ='SCI 34 RUE HAUTE'!H47+'SCI LEGRAND'!H47+'SCI ARMEE ORIENT'!H47+'SCI CHENNEVIERES'!H47+'SCI TAVERNY'!H47+'SCI GENERAL JULES BRIMONT'!H47 -> 8940.64
D48: 61600300 ASSURANCE MULTIRISQUE | E48: ='SCI 34 RUE HAUTE'!E48+'SCI LEGRAND'!E48+'SCI ARMEE ORIENT'!E48+'SCI CHENNEVIERES'!E48+'SCI TAVERNY'!E48+'SCI GENERAL JULES BRIMONT'!E48 -> 0 | F48: ='SCI 34 RUE HAUTE'!F48+'SCI LEGRAND'!F48+'SCI ARMEE ORIENT'!F48+'SCI CHENNEVIERES'!F48+'SCI TAVERNY'!F48+'SCI GENERAL JULES BRIMONT'!F48 -> 87 | G48: ='SCI 34 RUE HAUTE'!G48+'SCI LEGRAND'!G48+'SCI ARMEE ORIENT'!G48+'SCI CHENNEVIERES'!G48+'SCI TAVERNY'!G48+'SCI GENERAL JULES BRIMONT'!G48 -> 95.5 | H48: ='SCI 34 RUE HAUTE'!H48+'SCI LEGRAND'!H48+'SCI ARMEE ORIENT'!H48+'SCI CHENNEVIERES'!H48+'SCI TAVERNY'!H48+'SCI GENERAL JULES BRIMONT'!H48 -> 93.075
D49: 62260000 HONORAIRES COMPTABLES | E49: ='SCI 34 RUE HAUTE'!E49+'SCI LEGRAND'!E49+'SCI ARMEE ORIENT'!E49+'SCI CHENNEVIERES'!E49+'SCI TAVERNY'!E49+'SCI GENERAL JULES BRIMONT'!E49 -> 11823 | F49: ='SCI 34 RUE HAUTE'!F49+'SCI LEGRAND'!F49+'SCI ARMEE ORIENT'!F49+'SCI CHENNEVIERES'!F49+'SCI TAVERNY'!F49+'SCI GENERAL JULES BRIMONT'!F49 -> 8616 | G49: ='SCI 34 RUE HAUTE'!G49+'SCI LEGRAND'!G49+'SCI ARMEE ORIENT'!G49+'SCI CHENNEVIERES'!G49+'SCI TAVERNY'!G49+'SCI GENERAL JULES BRIMONT'!G49 -> 8788 | H49: ='SCI 34 RUE HAUTE'!H49+'SCI LEGRAND'!H49+'SCI ARMEE ORIENT'!H49+'SCI CHENNEVIERES'!H49+'SCI TAVERNY'!H49+'SCI GENERAL JULES BRIMONT'!H49 -> 8963.76
D50: 62262000 HONORAIRES JURIDIQUES | E50: ='SCI 34 RUE HAUTE'!E50+'SCI LEGRAND'!E50+'SCI ARMEE ORIENT'!E50+'SCI CHENNEVIERES'!E50+'SCI TAVERNY'!E50+'SCI GENERAL JULES BRIMONT'!E50 -> 6577 | F50: ='SCI 34 RUE HAUTE'!F50+'SCI LEGRAND'!F50+'SCI ARMEE ORIENT'!F50+'SCI CHENNEVIERES'!F50+'SCI TAVERNY'!F50+'SCI GENERAL JULES BRIMONT'!F50 -> 1880 | G50: ='SCI 34 RUE HAUTE'!G50+'SCI LEGRAND'!G50+'SCI ARMEE ORIENT'!G50+'SCI CHENNEVIERES'!G50+'SCI TAVERNY'!G50+'SCI GENERAL JULES BRIMONT'!G50 -> 1879 | H50: ='SCI 34 RUE HAUTE'!H50+'SCI LEGRAND'!H50+'SCI ARMEE ORIENT'!H50+'SCI CHENNEVIERES'!H50+'SCI TAVERNY'!H50+'SCI GENERAL JULES BRIMONT'!H50 -> 1916.58
D51: 62268000 HONORAIRES DIVERS | E51: ='SCI 34 RUE HAUTE'!E51+'SCI LEGRAND'!E51+'SCI ARMEE ORIENT'!E51+'SCI CHENNEVIERES'!E51+'SCI TAVERNY'!E51+'SCI GENERAL JULES BRIMONT'!E51 -> 107423 | F51: ='SCI 34 RUE HAUTE'!F51+'SCI LEGRAND'!F51+'SCI ARMEE ORIENT'!F51+'SCI CHENNEVIERES'!F51+'SCI TAVERNY'!F51+'SCI GENERAL JULES BRIMONT'!F51 -> 99209 | G51: ='SCI 34 RUE HAUTE'!G51+'SCI LEGRAND'!G51+'SCI ARMEE ORIENT'!G51+'SCI CHENNEVIERES'!G51+'SCI TAVERNY'!G51+'SCI GENERAL JULES BRIMONT'!G51 -> 23604 | H51: ='SCI 34 RUE HAUTE'!H51+'SCI LEGRAND'!H51+'SCI ARMEE ORIENT'!H51+'SCI CHENNEVIERES'!H51+'SCI TAVERNY'!H51+'SCI GENERAL JULES BRIMONT'!H51 -> 24076.08
... D54: 62780000 FRAIS BANCAIRES | E54: ='SCI 34 RUE HAUTE'!E54+'SCI LEGRAND'!E54+'SCI ARMEE ORIENT'!E54+'SCI CHENNEVIERES'!E54+'SCI TAVERNY'!E54+'SCI GENERAL JULES BRIMONT'!E54 -> 2193 | F54: ='SCI 34 RUE HAUTE'!F54+'SCI LEGRAND'!F54+'SCI ARMEE ORIENT'!F54+'SCI CHENNEVIERES'!F54+'SCI TAVERNY'!F54+'SCI GENERAL JULES BRIMONT'!F54 -> 6170 | G54: ='SCI 34 RUE HAUTE'!G54+'SCI LEGRAND'!G54+'SCI ARMEE ORIENT'!G54+'SCI CHENNEVIERES'!G54+'SCI TAVERNY'!G54+'SCI GENERAL JULES BRIMONT'!G54 -> 5931 | H54: ='SCI 34 RUE HAUTE'!H54+'SCI LEGRAND'!H54+'SCI ARMEE ORIENT'!H54+'SCI CHENNEVIERES'!H54+'SCI TAVERNY'!H54+'SCI GENERAL JULES BRIMONT'!H54 -> 3787.6
D55: IMPOTS, TAXES ET VERSEMENTS ASSIMILES | E55: =E56+E57 -> 22439 | F55: =F56+F57 -> 56021 | G55: =G56+G57 -> 61996 | H55: =H56+H57 -> 63201.74
D56: 63512000 TAXE FONCIERES | E56: ='SCI 34 RUE HAUTE'!E56+'SCI LEGRAND'!E56+'SCI ARMEE ORIENT'!E56+'SCI CHENNEVIERES'!E56+'SCI TAVERNY'!E56+'SCI GENERAL JULES BRIMONT'!E56 -> 22439 | F56: ='SCI 34 RUE HAUTE'!F56+'SCI LEGRAND'!F56+'SCI ARMEE ORIENT'!F56+'SCI CHENNEVIERES'!F56+'SCI TAVERNY'!F56+'SCI GENERAL JULES BRIMONT'!F56 -> 54405 | G56: ='SCI 34 RUE HAUTE'!G56+'SCI LEGRAND'!G56+'SCI ARMEE ORIENT'!G56+'SCI CHENNEVIERES'!G56+'SCI TAVERNY'!G56+'SCI GENERAL JULES BRIMONT'!G56 -> 60287 | H56: ='SCI 34 RUE HAUTE'!H56+'SCI LEGRAND'!H56+'SCI ARMEE ORIENT'!H56+'SCI CHENNEVIERES'!H56+'SCI TAVERNY'!H56+'SCI GENERAL JULES BRIMONT'!H56 -> 61492.74
D57: 63513000 TAXE ORDURES MENAGERES et autres | E57: ='SCI 34 RUE HAUTE'!E57+'SCI LEGRAND'!E57+'SCI ARMEE ORIENT'!E57+'SCI CHENNEVIERES'!E57+'SCI TAVERNY'!E57+'SCI GENERAL JULES BRIMONT'!E57 -> 0 | F57: ='SCI 34 RUE HAUTE'!F57+'SCI LEGRAND'!F57+'SCI ARMEE ORIENT'!F57+'SCI CHENNEVIERES'!F57+'SCI TAVERNY'!F57+'SCI GENERAL JULES BRIMONT'!F57 -> 1616 | G57: ='SCI 34 RUE HAUTE'!G57+'SCI LEGRAND'!G57+'SCI ARMEE ORIENT'!G57+'SCI CHENNEVIERES'!G57+'SCI TAVERNY'!G57+'SCI GENERAL JULES BRIMONT'!G57 -> 1709 | H57: ='SCI 34 RUE HAUTE'!H57+'SCI LEGRAND'!H57+'SCI ARMEE ORIENT'!H57+'SCI CHENNEVIERES'!H57+'SCI TAVERNY'!H57+'SCI GENERAL JULES BRIMONT'!H57 -> 1709
D58: DOTATIONS AUX AMORTISSEMENTS SUR IMMOBILISATIONS | E58: =E59 -> 155381 | F58: =F59 -> 283652 | G58: =G59 -> 283652 | H58: =H59 -> 330652
D59: 68112000 DOTATION AMORT. IMMOB.CORP. | E59: ='SCI 34 RUE HAUTE'!E59+'SCI LEGRAND'!E59+'SCI ARMEE ORIENT'!E59+'SCI CHENNEVIERES'!E59+'SCI TAVERNY'!E59+'SCI GENERAL JULES BRIMONT'!E59 -> 155381 | F59: ='SCI 34 RUE HAUTE'!F59+'SCI LEGRAND'!F59+'SCI ARMEE ORIENT'!F59+'SCI CHENNEVIERES'!F59+'SCI TAVERNY'!F59+'SCI GENERAL JULES BRIMONT'!F59 -> 283652 | G59: ='SCI 34 RUE HAUTE'!G59+'SCI LEGRAND'!G59+'SCI ARMEE ORIENT'!G59+'SCI CHENNEVIERES'!G59+'SCI TAVERNY'!G59+'SCI GENERAL JULES BRIMONT'!G59 -> 283652 | H59: ='SCI 34 RUE HAUTE'!H59+'SCI LEGRAND'!H59+'SCI ARMEE ORIENT'!H59+'SCI CHENNEVIERES'!H59+'SCI TAVERNY'!H59+'SCI GENERAL JULES BRIMONT'!H59 -> 330652
D60: AUTRES CHARGES | E60: =E61 -> 0 | F60: =F61 -> 127 | G60: =G61 -> 0 | H60: =H61 -> 0
D61: 65800000 CHARGES DE GESTION COURANTE | E61: ='SCI 34 RUE HAUTE'!E61+'SCI LEGRAND'!E61+'SCI ARMEE ORIENT'!E61+'SCI CHENNEVIERES'!E61+'SCI TAVERNY'!E61+'SCI GENERAL JULES BRIMONT'!E61 -> 0 | F61: ='SCI 34 RUE HAUTE'!F61+'SCI LEGRAND'!F61+'SCI ARMEE ORIENT'!F61+'SCI CHENNEVIERES'!F61+'SCI TAVERNY'!F61+'SCI GENERAL JULES BRIMONT'!F61 -> 127 | G61: ='SCI 34 RUE HAUTE'!G61+'SCI LEGRAND'!G61+'SCI ARMEE ORIENT'!G61+'SCI CHENNEVIERES'!G61+'SCI TAVERNY'!G61+'SCI GENERAL JULES BRIMONT'!G61 -> 0 | H61: ='SCI 34 RUE HAUTE'!H61+'SCI LEGRAND'!H61+'SCI ARMEE ORIENT'!H61+'SCI CHENNEVIERES'!H61+'SCI TAVERNY'!H61+'SCI GENERAL JULES BRIMONT'!H61 -> 0
D62: Total des Charges d'exploitation | E62: =E60+E58+E55+E39 -> 594584 | F62: =F60+F58+F55+F39 -> 603473 | G62: =G60+G58+G55+G39 -> 496055.07 | H62: =H60+H58+H55+H39 -> 546868.92
D63: Résultat d'exploitation | E63: =E38-E62 -> -210207 | F63: =F38-F62 -> 49076 | G63: =G38-G62 -> 415695.93 | H63: =H38-H62 -> 456771.41
D64: INTERETS ET CHARGES ASSIMILEES | E64: =E65+E66 -> 116677 | F64: =F65+F66 -> 246885 | G64: =G65+G66 -> 252035 | H64: =H65+H66 -> 257833.8
D65: 66100000 INTERETS BANCAIRES | E65: ='SCI 34 RUE HAUTE'!E65+'SCI LEGRAND'!E65+'SCI ARMEE ORIENT'!E65+'SCI CHENNEVIERES'!E65+'SCI TAVERNY'!E65+'SCI GENERAL JULES BRIMONT'!E65 -> 0 | F65: ='SCI 34 RUE HAUTE'!F65+'SCI LEGRAND'!F65+'SCI ARMEE ORIENT'!F65+'SCI CHENNEVIERES'!F65+'SCI TAVERNY'!F65+'SCI GENERAL JULES BRIMONT'!F65 -> 54 | G65: ='SCI 34 RUE HAUTE'!G65+'SCI LEGRAND'!G65+'SCI ARMEE ORIENT'!G65+'SCI CHENNEVIERES'!G65+'SCI TAVERNY'!G65+'SCI GENERAL JULES BRIMONT'!G65 -> 1 | H65: ='SCI 34 RUE HAUTE'!H65+'SCI LEGRAND'!H65+'SCI ARMEE ORIENT'!H65+'SCI CHENNEVIERES'!H65+'SCI TAVERNY'!H65+'SCI GENERAL JULES BRIMONT'!H65 -> 0
D66: 66112000 INTERETS DES EMPRUNTS - CE | E66: ='SCI 34 RUE HAUTE'!E66+'SCI LEGRAND'!E66+'SCI ARMEE ORIENT'!E66+'SCI CHENNEVIERES'!E66+'SCI TAVERNY'!E66+'SCI GENERAL JULES BRIMONT'!E66 -> 116677 | F66: ='SCI 34 RUE HAUTE'!F66+'SCI LEGRAND'!F66+'SCI ARMEE ORIENT'!F66+'SCI CHENNEVIERES'!F66+'SCI TAVERNY'!F66+'SCI GENERAL JULES BRIMONT'!F66 -> 246831 | G66: ='SCI 34 RUE HAUTE'!G66+'SCI LEGRAND'!G66+'SCI ARMEE ORIENT'!G66+'SCI CHENNEVIERES'!G66+'SCI TAVERNY'!G66+'SCI GENERAL JULES BRIMONT'!G66 -> 252034 | H66: ='SCI 34 RUE HAUTE'!H66+'SCI LEGRAND'!H66+'SCI ARMEE ORIENT'!H66+'SCI CHENNEVIERES'!H66+'SCI TAVERNY'!H66+'SCI GENERAL JULES BRIMONT'!H66 -> 257833.8
D67: Total des Charges financières | E67: =E64 -> 116677 | F67: =F64 -> 246885 | G67: =G64 -> 252035 | H67: =H64 -> 257833.8
D68: Résultat financier | E68: =E67 -> 116677 | F68: =F67 -> 246885 | G68: =G67 -> 252035 | H68: =H67 -> 257833.8
D69: Résultat courant avant impôts | E69: =E63-E68 -> -326884 | F69: =F63-F68 -> -197809 | G69: =G63-G68 -> 163660.93 | H69: =H63-H68 -> 198937.62
D70: 69500000 IS
D71: Résultat NET | E71: =E69-E70 -> -326884 | F71: =F69-F70 -> -197809 | G71: =G69-G70 -> 163660.93 | H71: =H69-H70 -> 198937.62
D73: IMMOBILISATIONS VO | E73: =SUM(E74:E84) -> 5612145 | F73: =SUM(F74:F84) -> 8878120 | G73: =SUM(G74:G84) -> 8883826 | H73: =SUM(H74:H84) -> 940000
D74: TERRAIN | E74: ='SCI 34 RUE HAUTE'!E74+'SCI LEGRAND'!E74+'SCI ARMEE ORIENT'!E74+'SCI CHENNEVIERES'!E74+'SCI TAVERNY'!E74+'SCI GENERAL JULES BRIMONT'!E74 -> 1251372 | F74: ='SCI 34 RUE HAUTE'!F74+'SCI LEGRAND'!F74+'SCI ARMEE ORIENT'!F74+'SCI CHENNEVIERES'!F74+'SCI TAVERNY'!F74+'SCI GENERAL JULES BRIMONT'!F74 -> 2815097 | G74: ='SCI 34 RUE HAUTE'!G74+'SCI LEGRAND'!G74+'SCI ARMEE ORIENT'!G74+'SCI CHENNEVIERES'!G74+'SCI TAVERNY'!G74+'SCI GENERAL JULES BRIMONT'!G74 -> 2815097 | H74: ='SCI 34 RUE HAUTE'!H74+'SCI LEGRAND'!H74+'SCI ARMEE ORIENT'!H74+'SCI CHENNEVIERES'!H74+'SCI TAVERNY'!H74+'SCI GENERAL JULES BRIMONT'!H74 -> 940000
D75: AGENCEMENTS TERRAIN | E75: ='SCI 34 RUE HAUTE'!E75+'SCI LEGRAND'!E75+'SCI ARMEE ORIENT'!E75+'SCI CHENNEVIERES'!E75+'SCI TAVERNY'!E75+'SCI GENERAL JULES BRIMONT'!E75 -> 97721 | F75: ='SCI 34 RUE HAUTE'!F75+'SCI LEGRAND'!F75+'SCI ARMEE ORIENT'!F75+'SCI CHENNEVIERES'!F75+'SCI TAVERNY'!F75+'SCI GENERAL JULES BRIMONT'!F75 -> 90581 | G75: ='SCI 34 RUE HAUTE'!G75+'SCI LEGRAND'!G75+'SCI ARMEE ORIENT'!G75+'SCI CHENNEVIERES'!G75+'SCI TAVERNY'!G75+'SCI GENERAL JULES BRIMONT'!G75 -> 0 | H75: ='SCI 34 RUE HAUTE'!H75+'SCI LEGRAND'!H75+'SCI ARMEE ORIENT'!H75+'SCI CHENNEVIERES'!H75+'SCI TAVERNY'!H75+'SCI GENERAL JULES BRIMONT'!H75 -> 0
D76: GROS ŒUVRE CRECHE | E76: ='SCI 34 RUE HAUTE'!E76+'SCI LEGRAND'!E76+'SCI ARMEE ORIENT'!E76+'SCI CHENNEVIERES'!E76+'SCI TAVERNY'!E76+'SCI GENERAL JULES BRIMONT'!E76 -> 1605337 | F76: ='SCI 34 RUE HAUTE'!F76+'SCI LEGRAND'!F76+'SCI ARMEE ORIENT'!F76+'SCI CHENNEVIERES'!F76+'SCI TAVERNY'!F76+'SCI GENERAL JULES BRIMONT'!F76 -> 2427444 | G76: ='SCI 34 RUE HAUTE'!G76+'SCI LEGRAND'!G76+'SCI ARMEE ORIENT'!G76+'SCI CHENNEVIERES'!G76+'SCI TAVERNY'!G76+'SCI GENERAL JULES BRIMONT'!G76 -> 2887745 | H76: ='SCI 34 RUE HAUTE'!H76+'SCI LEGRAND'!H76+'SCI ARMEE ORIENT'!H76+'SCI CHENNEVIERES'!H76+'SCI TAVERNY'!H76+'SCI GENERAL JULES BRIMONT'!H76 -> 0
D77: GROS ŒUVRE LOGEMENTS | E77: ='SCI 34 RUE HAUTE'!E77+'SCI LEGRAND'!E77+'SCI ARMEE ORIENT'!E77+'SCI CHENNEVIERES'!E77+'SCI TAVERNY'!E77+'SCI GENERAL JULES BRIMONT'!E77 -> 472509 | F77: ='SCI 34 RUE HAUTE'!F77+'SCI LEGRAND'!F77+'SCI ARMEE ORIENT'!F77+'SCI CHENNEVIERES'!F77+'SCI TAVERNY'!F77+'SCI GENERAL JULES BRIMONT'!F77 -> 485310 | G77: ='SCI 34 RUE HAUTE'!G77+'SCI LEGRAND'!G77+'SCI ARMEE ORIENT'!G77+'SCI CHENNEVIERES'!G77+'SCI TAVERNY'!G77+'SCI GENERAL JULES BRIMONT'!G77 -> 0 | H77: ='SCI 34 RUE HAUTE'!H77+'SCI LEGRAND'!H77+'SCI ARMEE ORIENT'!H77+'SCI CHENNEVIERES'!H77+'SCI TAVERNY'!H77+'SCI GENERAL JULES BRIMONT'!H77 -> 0
D78: FACADE ETANCHEITE CRECHE | E78: ='SCI 34 RUE HAUTE'!E78+'SCI LEGRAND'!E78+'SCI ARMEE ORIENT'!E78+'SCI CHENNEVIERES'!E78+'SCI TAVERNY'!E78+'SCI GENERAL JULES BRIMONT'!E78 -> 761619 | F78: ='SCI 34 RUE HAUTE'!F78+'SCI LEGRAND'!F78+'SCI ARMEE ORIENT'!F78+'SCI CHENNEVIERES'!F78+'SCI TAVERNY'!F78+'SCI GENERAL JULES BRIMONT'!F78 -> 1166569 | G78: ='SCI 34 RUE HAUTE'!G78+'SCI LEGRAND'!G78+'SCI ARMEE ORIENT'!G78+'SCI CHENNEVIERES'!G78+'SCI TAVERNY'!G78+'SCI GENERAL JULES BRIMONT'!G78 -> 1166569 | H78: ='SCI 34 RUE HAUTE'!H78+'SCI LEGRAND'!H78+'SCI ARMEE ORIENT'!H78+'SCI CHENNEVIERES'!H78+'SCI TAVERNY'!H78+'SCI GENERAL JULES BRIMONT'!H78 -> 0
D79: FACADE ETANCHEITE LOGEMENTS | E79: ='SCI 34 RUE HAUTE'!E79+'SCI LEGRAND'!E79+'SCI ARMEE ORIENT'!E79+'SCI CHENNEVIERES'!E79+'SCI TAVERNY'!E79+'SCI GENERAL JULES BRIMONT'!E79 -> 118205 | F79: ='SCI 34 RUE HAUTE'!F79+'SCI LEGRAND'!F79+'SCI ARMEE ORIENT'!F79+'SCI CHENNEVIERES'!F79+'SCI TAVERNY'!F79+'SCI GENERAL JULES BRIMONT'!F79 -> 118205 | G79: ='SCI 34 RUE HAUTE'!G79+'SCI LEGRAND'!G79+'SCI ARMEE ORIENT'!G79+'SCI CHENNEVIERES'!G79+'SCI TAVERNY'!G79+'SCI GENERAL JULES BRIMONT'!G79 -> 118205 | H79: ='SCI 34 RUE HAUTE'!H79+'SCI LEGRAND'!H79+'SCI ARMEE ORIENT'!H79+'SCI CHENNEVIERES'!H79+'SCI TAVERNY'!H79+'SCI GENERAL JULES BRIMONT'!H79 -> 0
D80: INSTALLATIONS CRECHE | E80: ='SCI 34 RUE HAUTE'!E80+'SCI LEGRAND'!E80+'SCI ARMEE ORIENT'!E80+'SCI CHENNEVIERES'!E80+'SCI TAVERNY'!E80+'SCI GENERAL JULES BRIMONT'!E80 -> 612174 | F80: ='SCI 34 RUE HAUTE'!F80+'SCI LEGRAND'!F80+'SCI ARMEE ORIENT'!F80+'SCI CHENNEVIERES'!F80+'SCI TAVERNY'!F80+'SCI GENERAL JULES BRIMONT'!F80 -> 855144 | G80: ='SCI 34 RUE HAUTE'!G80+'SCI LEGRAND'!G80+'SCI ARMEE ORIENT'!G80+'SCI CHENNEVIERES'!G80+'SCI TAVERNY'!G80+'SCI GENERAL JULES BRIMONT'!G80 -> 855144 | H80: ='SCI 34 RUE HAUTE'!H80+'SCI LEGRAND'!H80+'SCI ARMEE ORIENT'!H80+'SCI CHENNEVIERES'!H80+'SCI TAVERNY'!H80+'SCI GENERAL JULES BRIMONT'!H80 -> 0
D81: INSTALLATIONS LOGEMENTS | E81: ='SCI 34 RUE HAUTE'!E81+'SCI LEGRAND'!E81+'SCI ARMEE ORIENT'!E81+'SCI CHENNEVIERES'!E81+'SCI TAVERNY'!E81+'SCI GENERAL JULES BRIMONT'!E81 -> 274743 | F81: ='SCI 34 RUE HAUTE'!F81+'SCI LEGRAND'!F81+'SCI ARMEE ORIENT'!F81+'SCI CHENNEVIERES'!F81+'SCI TAVERNY'!F81+'SCI GENERAL JULES BRIMONT'!F81 -> 274743 | G81: ='SCI 34 RUE HAUTE'!G81+'SCI LEGRAND'!G81+'SCI ARMEE ORIENT'!G81+'SCI CHENNEVIERES'!G81+'SCI TAVERNY'!G81+'SCI GENERAL JULES BRIMONT'!G81 -> 274743 | H81: ='SCI 34 RUE HAUTE'!H81+'SCI LEGRAND'!H81+'SCI ARMEE ORIENT'!H81+'SCI CHENNEVIERES'!H81+'SCI TAVERNY'!H81+'SCI GENERAL JULES BRIMONT'!H81 -> 0
D82: AGENCEMENTS CRECHE | E82: ='SCI 34 RUE HAUTE'!E82+'SCI LEGRAND'!E82+'SCI ARMEE ORIENT'!E82+'SCI CHENNEVIERES'!E82+'SCI TAVERNY'!E82+'SCI GENERAL JULES BRIMONT'!E82 -> 321638 | F82: ='SCI 34 RUE HAUTE'!F82+'SCI LEGRAND'!F82+'SCI ARMEE ORIENT'!F82+'SCI CHENNEVIERES'!F82+'SCI TAVERNY'!F82+'SCI GENERAL JULES BRIMONT'!F82 -> 483618 | G82: ='SCI 34 RUE HAUTE'!G82+'SCI LEGRAND'!G82+'SCI ARMEE ORIENT'!G82+'SCI CHENNEVIERES'!G82+'SCI TAVERNY'!G82+'SCI GENERAL JULES BRIMONT'!G82 -> 678165 | H82: ='SCI 34 RUE HAUTE'!H82+'SCI LEGRAND'!H82+'SCI ARMEE ORIENT'!H82+'SCI CHENNEVIERES'!H82+'SCI TAVERNY'!H82+'SCI GENERAL JULES BRIMONT'!H82 -> 0
D83: AGENCEMENTS LOGEMENTS | E83: ='SCI 34 RUE HAUTE'!E83+'SCI LEGRAND'!E83+'SCI ARMEE ORIENT'!E83+'SCI CHENNEVIERES'!E83+'SCI TAVERNY'!E83+'SCI GENERAL JULES BRIMONT'!E83 -> 87483 | F83: ='SCI 34 RUE HAUTE'!F83+'SCI LEGRAND'!F83+'SCI ARMEE ORIENT'!F83+'SCI CHENNEVIERES'!F83+'SCI TAVERNY'!F83+'SCI GENERAL JULES BRIMONT'!F83 -> 87483 | G83: ='SCI 34 RUE HAUTE'!G83+'SCI LEGRAND'!G83+'SCI ARMEE ORIENT'!G83+'SCI CHENNEVIERES'!G83+'SCI TAVERNY'!G83+'SCI GENERAL JULES BRIMONT'!G83 -> 17867 | H83: ='SCI 34 RUE HAUTE'!H83+'SCI LEGRAND'!H83+'SCI ARMEE ORIENT'!H83+'SCI CHENNEVIERES'!H83+'SCI TAVERNY'!H83+'SCI GENERAL JULES BRIMONT'!H83 -> 0
D84: AGENCEMENTS SUPPL LOGEMENTS | E84: ='SCI 34 RUE HAUTE'!E84+'SCI LEGRAND'!E84+'SCI ARMEE ORIENT'!E84+'SCI CHENNEVIERES'!E84+'SCI TAVERNY'!E84+'SCI GENERAL JULES BRIMONT'!E84 -> 9344 | F84: ='SCI 34 RUE HAUTE'!F84+'SCI LEGRAND'!F84+'SCI ARMEE ORIENT'!F84+'SCI CHENNEVIERES'!F84+'SCI TAVERNY'!F84+'SCI GENERAL JULES BRIMONT'!F84 -> 73926 | G84: ='SCI 34 RUE HAUTE'!G84+'SCI LEGRAND'!G84+'SCI ARMEE ORIENT'!G84+'SCI CHENNEVIERES'!G84+'SCI TAVERNY'!G84+'SCI GENERAL JULES BRIMONT'!G84 -> 70291 | H84: ='SCI 34 RUE HAUTE'!H84+'SCI LEGRAND'!H84+'SCI ARMEE ORIENT'!H84+'SCI CHENNEVIERES'!H84+'SCI TAVERNY'!H84+'SCI GENERAL JULES BRIMONT'!H84 -> 0
D86: FINANCEMENTS IMMO | E86: =SUM(E87:E92) -> 9457645 | F86: =SUM(F87:F92) -> 10944836 | G86: =SUM(G87:G92) -> 8909535 | H86: =SUM(H87:H92) -> 0
D87: EMPRUNT CE VO | E87: ='SCI 34 RUE HAUTE'!E87+'SCI LEGRAND'!E87+'SCI ARMEE ORIENT'!E87+'SCI CHENNEVIERES'!E87+'SCI TAVERNY'!E87+'SCI GENERAL JULES BRIMONT'!E87 -> 3635535 | F87: ='SCI 34 RUE HAUTE'!F87+'SCI LEGRAND'!F87+'SCI ARMEE ORIENT'!F87+'SCI CHENNEVIERES'!F87+'SCI TAVERNY'!F87+'SCI GENERAL JULES BRIMONT'!F87 -> 4369535 | G87: ='SCI 34 RUE HAUTE'!G87+'SCI LEGRAND'!G87+'SCI ARMEE ORIENT'!G87+'SCI CHENNEVIERES'!G87+'SCI TAVERNY'!G87+'SCI GENERAL JULES BRIMONT'!G87 -> 2960612 | H87: ='SCI 34 RUE HAUTE'!H87+'SCI LEGRAND'!H87+'SCI ARMEE ORIENT'!H87+'SCI CHENNEVIERES'!H87+'SCI TAVERNY'!H87+'SCI GENERAL JULES BRIMONT'!H87 -> 0
D88: EMPRUNT CE VO | E88: ='SCI 34 RUE HAUTE'!E88+'SCI LEGRAND'!E88+'SCI ARMEE ORIENT'!E88+'SCI CHENNEVIERES'!E88+'SCI TAVERNY'!E88+'SCI GENERAL JULES BRIMONT'!E88 -> 5108923 | F88: ='SCI 34 RUE HAUTE'!F88+'SCI LEGRAND'!F88+'SCI ARMEE ORIENT'!F88+'SCI CHENNEVIERES'!F88+'SCI TAVERNY'!F88+'SCI GENERAL JULES BRIMONT'!F88 -> 5948923 | G88: ='SCI 34 RUE HAUTE'!G88+'SCI LEGRAND'!G88+'SCI ARMEE ORIENT'!G88+'SCI CHENNEVIERES'!G88+'SCI TAVERNY'!G88+'SCI GENERAL JULES BRIMONT'!G88 -> 5948923 | H88: ='SCI 34 RUE HAUTE'!H88+'SCI LEGRAND'!H88+'SCI ARMEE ORIENT'!H88+'SCI CHENNEVIERES'!H88+'SCI TAVERNY'!H88+'SCI GENERAL JULES BRIMONT'!H88 -> 0
D89: C/C GROUPE | E89: ='SCI 34 RUE HAUTE'!E89+'SCI LEGRAND'!E89+'SCI ARMEE ORIENT'!E89+'SCI CHENNEVIERES'!E89+'SCI TAVERNY'!E89+'SCI GENERAL JULES BRIMONT'!E89 -> 0 | F89: ='SCI 34 RUE HAUTE'!F89+'SCI LEGRAND'!F89+'SCI ARMEE ORIENT'!F89+'SCI CHENNEVIERES'!F89+'SCI TAVERNY'!F89+'SCI GENERAL JULES BRIMONT'!F89 -> 0 | G89: ='SCI 34 RUE HAUTE'!G89+'SCI LEGRAND'!G89+'SCI ARMEE ORIENT'!G89+'SCI CHENNEVIERES'!G89+'SCI TAVERNY'!G89+'SCI GENERAL JULES BRIMONT'!G89 -> 0 | H89: ='SCI 34 RUE HAUTE'!H89+'SCI LEGRAND'!H89+'SCI ARMEE ORIENT'!H89+'SCI CHENNEVIERES'!H89+'SCI TAVERNY'!H89+'SCI GENERAL JULES BRIMONT'!H89 -> 0
D90: C/C HIO SARLU | E90: ='SCI 34 RUE HAUTE'!E90+'SCI LEGRAND'!E90+'SCI ARMEE ORIENT'!E90+'SCI CHENNEVIERES'!E90+'SCI TAVERNY'!E90+'SCI GENERAL JULES BRIMONT'!E90 -> 209305 | F90: ='SCI 34 RUE HAUTE'!F90+'SCI LEGRAND'!F90+'SCI ARMEE ORIENT'!F90+'SCI CHENNEVIERES'!F90+'SCI TAVERNY'!F90+'SCI GENERAL JULES BRIMONT'!F90 -> 301421 | G90: ='SCI 34 RUE HAUTE'!G90+'SCI LEGRAND'!G90+'SCI ARMEE ORIENT'!G90+'SCI CHENNEVIERES'!G90+'SCI TAVERNY'!G90+'SCI GENERAL JULES BRIMONT'!G90 -> 0 | H90: ='SCI 34 RUE HAUTE'!H90+'SCI LEGRAND'!H90+'SCI ARMEE ORIENT'!H90+'SCI CHENNEVIERES'!H90+'SCI TAVERNY'!H90+'SCI GENERAL JULES BRIMONT'!H90 -> 0
D91: C/C AXORIEL SARLU | E91: ='SCI 34 RUE HAUTE'!E91+'SCI LEGRAND'!E91+'SCI ARMEE ORIENT'!E91+'SCI CHENNEVIERES'!E91+'SCI TAVERNY'!E91+'SCI GENERAL JULES BRIMONT'!E91 -> 249728 | F91: ='SCI 34 RUE HAUTE'!F91+'SCI LEGRAND'!F91+'SCI ARMEE ORIENT'!F91+'SCI CHENNEVIERES'!F91+'SCI TAVERNY'!F91+'SCI GENERAL JULES BRIMONT'!F91 -> 310344 | G91: ='SCI 34 RUE HAUTE'!G91+'SCI LEGRAND'!G91+'SCI ARMEE ORIENT'!G91+'SCI CHENNEVIERES'!G91+'SCI TAVERNY'!G91+'SCI GENERAL JULES BRIMONT'!G91 -> 0 | H91: ='SCI 34 RUE HAUTE'!H91+'SCI LEGRAND'!H91+'SCI ARMEE ORIENT'!H91+'SCI CHENNEVIERES'!H91+'SCI TAVERNY'!H91+'SCI GENERAL JULES BRIMONT'!H91 -> 0
D92: DETTE FRS | E92: ='SCI 34 RUE HAUTE'!E92+'SCI LEGRAND'!E92+'SCI ARMEE ORIENT'!E92+'SCI CHENNEVIERES'!E92+'SCI TAVERNY'!E92+'SCI GENERAL JULES BRIMONT'!E92 -> 254154 | F92: ='SCI 34 RUE HAUTE'!F92+'SCI LEGRAND'!F92+'SCI ARMEE ORIENT'!F92+'SCI CHENNEVIERES'!F92+'SCI TAVERNY'!F92+'SCI GENERAL JULES BRIMONT'!F92 -> 14613 | G92: ='SCI 34 RUE HAUTE'!G92+'SCI LEGRAND'!G92+'SCI ARMEE ORIENT'!G92+'SCI CHENNEVIERES'!G92+'SCI TAVERNY'!G92+'SCI GENERAL JULES BRIMONT'!G92 -> 0 | H92: ='SCI 34 RUE HAUTE'!H92+'SCI LEGRAND'!H92+'SCI ARMEE ORIENT'!H92+'SCI CHENNEVIERES'!H92+'SCI TAVERNY'!H92+'SCI GENERAL JULES BRIMONT'!H92 -> 0
B95: Année fin | C95: Taux | D95: DETTES RESTANTES | E95: =SUM(E96:E107) -> 8824791 | F95: =SUM(F96:F107) -> 9454038 | G95: =SUM(G96:G107) -> 8488688.4 | H95: =SUM(H96:H107) -> 1610125.6
B96: 2035 | C96: 0.0135 | D96: EMPRUNT CE 409k€ | E96: ='SCI 34 RUE HAUTE'!E96+'SCI LEGRAND'!E96+'SCI ARMEE ORIENT'!E96+'SCI CHENNEVIERES'!E96+'SCI TAVERNY'!E96+'SCI GENERAL JULES BRIMONT'!E96 -> 3229589 | F96: ='SCI 34 RUE HAUTE'!F96+'SCI LEGRAND'!F96+'SCI ARMEE ORIENT'!F96+'SCI CHENNEVIERES'!F96+'SCI TAVERNY'!F96+'SCI GENERAL JULES BRIMONT'!F96 -> 3593114 | G96: ='SCI 34 RUE HAUTE'!G96+'SCI LEGRAND'!G96+'SCI ARMEE ORIENT'!G96+'SCI CHENNEVIERES'!G96+'SCI TAVERNY'!G96+'SCI GENERAL JULES BRIMONT'!G96 -> 3339373.8 | H96: ='SCI 34 RUE HAUTE'!H96+'SCI LEGRAND'!H96+'SCI ARMEE ORIENT'!H96+'SCI CHENNEVIERES'!H96+'SCI TAVERNY'!H96+'SCI GENERAL JULES BRIMONT'!H96 -> 277076.48
B97: 2036 | C97: 0.0135 | D97: EMPRUNT CE 1515k€ | E97: ='SCI 34 RUE HAUTE'!E97+'SCI LEGRAND'!E97+'SCI ARMEE ORIENT'!E97+'SCI CHENNEVIERES'!E97+'SCI TAVERNY'!E97+'SCI GENERAL JULES BRIMONT'!E97 -> 4591970 | F97: ='SCI 34 RUE HAUTE'!F97+'SCI LEGRAND'!F97+'SCI ARMEE ORIENT'!F97+'SCI CHENNEVIERES'!F97+'SCI TAVERNY'!F97+'SCI GENERAL JULES BRIMONT'!F97 -> 4845505 | G97: ='SCI 34 RUE HAUTE'!G97+'SCI LEGRAND'!G97+'SCI ARMEE ORIENT'!G97+'SCI CHENNEVIERES'!G97+'SCI TAVERNY'!G97+'SCI GENERAL JULES BRIMONT'!G97 -> 4567857.8 | H97: ='SCI 34 RUE HAUTE'!H97+'SCI LEGRAND'!H97+'SCI ARMEE ORIENT'!H97+'SCI CHENNEVIERES'!H97+'SCI TAVERNY'!H97+'SCI GENERAL JULES BRIMONT'!H97 -> 1070464.9
B98: 2032 | C98: 0.0353 | D98: EMPRUNT SG 350k€ | E98: ='SCI 34 RUE HAUTE'!E98+'SCI LEGRAND'!E98+'SCI ARMEE ORIENT'!E98+'SCI CHENNEVIERES'!E98+'SCI TAVERNY'!E98+'SCI GENERAL JULES BRIMONT'!E98 -> 0 | F98: ='SCI 34 RUE HAUTE'!F98+'SCI LEGRAND'!F98+'SCI ARMEE ORIENT'!F98+'SCI CHENNEVIERES'!F98+'SCI TAVERNY'!F98+'SCI GENERAL JULES BRIMONT'!F98 -> 0 | G98: ='SCI 34 RUE HAUTE'!G98+'SCI LEGRAND'!G98+'SCI ARMEE ORIENT'!G98+'SCI CHENNEVIERES'!G98+'SCI TAVERNY'!G98+'SCI GENERAL JULES BRIMONT'!G98 -> 308928.85 | H98: ='SCI 34 RUE HAUTE'!H98+'SCI LEGRAND'!H98+'SCI ARMEE ORIENT'!H98+'SCI CHENNEVIERES'!H98+'SCI TAVERNY'!H98+'SCI GENERAL JULES BRIMONT'!H98 -> 262584.23
D99: DG LOGEMENTS | E99: ='SCI 34 RUE HAUTE'!E99+'SCI LEGRAND'!E99+'SCI ARMEE ORIENT'!E99+'SCI CHENNEVIERES'!E99+'SCI TAVERNY'!E99+'SCI GENERAL JULES BRIMONT'!E99 -> 26166 | F99: ='SCI 34 RUE HAUTE'!F99+'SCI LEGRAND'!F99+'SCI ARMEE ORIENT'!F99+'SCI CHENNEVIERES'!F99+'SCI TAVERNY'!F99+'SCI GENERAL JULES BRIMONT'!F99 -> 55592 | G99: ='SCI 34 RUE HAUTE'!G99+'SCI LEGRAND'!G99+'SCI ARMEE ORIENT'!G99+'SCI CHENNEVIERES'!G99+'SCI TAVERNY'!G99+'SCI GENERAL JULES BRIMONT'!G99 -> 46975 | H99: ='SCI 34 RUE HAUTE'!H99+'SCI LEGRAND'!H99+'SCI ARMEE ORIENT'!H99+'SCI CHENNEVIERES'!H99+'SCI TAVERNY'!H99+'SCI GENERAL JULES BRIMONT'!H99 -> 0
D100: DG CRECHE | E100: ='SCI 34 RUE HAUTE'!E100+'SCI LEGRAND'!E100+'SCI ARMEE ORIENT'!E100+'SCI CHENNEVIERES'!E100+'SCI TAVERNY'!E100+'SCI GENERAL JULES BRIMONT'!E100 -> 45667 | F100: ='SCI 34 RUE HAUTE'!F100+'SCI LEGRAND'!F100+'SCI ARMEE ORIENT'!F100+'SCI CHENNEVIERES'!F100+'SCI TAVERNY'!F100+'SCI GENERAL JULES BRIMONT'!F100 -> 89210 | G100: ='SCI 34 RUE HAUTE'!G100+'SCI LEGRAND'!G100+'SCI ARMEE ORIENT'!G100+'SCI CHENNEVIERES'!G100+'SCI TAVERNY'!G100+'SCI GENERAL JULES BRIMONT'!G100 -> 66242 | H100: ='SCI 34 RUE HAUTE'!H100+'SCI LEGRAND'!H100+'SCI ARMEE ORIENT'!H100+'SCI CHENNEVIERES'!H100+'SCI TAVERNY'!H100+'SCI GENERAL JULES BRIMONT'!H100 -> 0
D101: C/C GROUPE | E101: ='SCI 34 RUE HAUTE'!E101+'SCI LEGRAND'!E101+'SCI ARMEE ORIENT'!E101+'SCI CHENNEVIERES'!E101+'SCI TAVERNY'!E101+'SCI GENERAL JULES BRIMONT'!E101 -> 111579 | F101: ='SCI 34 RUE HAUTE'!F101+'SCI LEGRAND'!F101+'SCI ARMEE ORIENT'!F101+'SCI CHENNEVIERES'!F101+'SCI TAVERNY'!F101+'SCI GENERAL JULES BRIMONT'!F101 -> 110108 | G101: ='SCI 34 RUE HAUTE'!G101+'SCI LEGRAND'!G101+'SCI ARMEE ORIENT'!G101+'SCI CHENNEVIERES'!G101+'SCI TAVERNY'!G101+'SCI GENERAL JULES BRIMONT'!G101 -> 149178 | H101: ='SCI 34 RUE HAUTE'!H101+'SCI LEGRAND'!H101+'SCI ARMEE ORIENT'!H101+'SCI CHENNEVIERES'!H101+'SCI TAVERNY'!H101+'SCI GENERAL JULES BRIMONT'!H101 -> 0
D102: C/C HIO SARLU | E102: ='SCI 34 RUE HAUTE'!E102+'SCI LEGRAND'!E102+'SCI ARMEE ORIENT'!E102+'SCI CHENNEVIERES'!E102+'SCI TAVERNY'!E102+'SCI GENERAL JULES BRIMONT'!E102 -> 210055 | F102: ='SCI 34 RUE HAUTE'!F102+'SCI LEGRAND'!F102+'SCI ARMEE ORIENT'!F102+'SCI CHENNEVIERES'!F102+'SCI TAVERNY'!F102+'SCI GENERAL JULES BRIMONT'!F102 -> 304697 | G102: ='SCI 34 RUE HAUTE'!G102+'SCI LEGRAND'!G102+'SCI ARMEE ORIENT'!G102+'SCI CHENNEVIERES'!G102+'SCI TAVERNY'!G102+'SCI GENERAL JULES BRIMONT'!G102 -> 0 | H102: ='SCI 34 RUE HAUTE'!H102+'SCI LEGRAND'!H102+'SCI ARMEE ORIENT'!H102+'SCI CHENNEVIERES'!H102+'SCI TAVERNY'!H102+'SCI GENERAL JULES BRIMONT'!H102 -> 0
D103: C/C AXORIEL SARLU | E103: ='SCI 34 RUE HAUTE'!E103+'SCI LEGRAND'!E103+'SCI ARMEE ORIENT'!E103+'SCI CHENNEVIERES'!E103+'SCI TAVERNY'!E103+'SCI GENERAL JULES BRIMONT'!E103 -> 249728 | F103: ='SCI 34 RUE HAUTE'!F103+'SCI LEGRAND'!F103+'SCI ARMEE ORIENT'!F103+'SCI CHENNEVIERES'!F103+'SCI TAVERNY'!F103+'SCI GENERAL JULES BRIMONT'!F103 -> 329322 | G103: ='SCI 34 RUE HAUTE'!G103+'SCI LEGRAND'!G103+'SCI ARMEE ORIENT'!G103+'SCI CHENNEVIERES'!G103+'SCI TAVERNY'!G103+'SCI GENERAL JULES BRIMONT'!G103 -> 0 | H103: ='SCI 34 RUE HAUTE'!H103+'SCI LEGRAND'!H103+'SCI ARMEE ORIENT'!H103+'SCI CHENNEVIERES'!H103+'SCI TAVERNY'!H103+'SCI GENERAL JULES BRIMONT'!H103 -> 0
D104: CLIENTS AV ET ACPTES RECUS | E104: ='SCI 34 RUE HAUTE'!E104+'SCI LEGRAND'!E104+'SCI ARMEE ORIENT'!E104+'SCI CHENNEVIERES'!E104+'SCI TAVERNY'!E104+'SCI GENERAL JULES BRIMONT'!E104 -> 46510 | F104: ='SCI 34 RUE HAUTE'!F104+'SCI LEGRAND'!F104+'SCI ARMEE ORIENT'!F104+'SCI CHENNEVIERES'!F104+'SCI TAVERNY'!F104+'SCI GENERAL JULES BRIMONT'!F104 -> 47399 | G104: ='SCI 34 RUE HAUTE'!G104+'SCI LEGRAND'!G104+'SCI ARMEE ORIENT'!G104+'SCI CHENNEVIERES'!G104+'SCI TAVERNY'!G104+'SCI GENERAL JULES BRIMONT'!G104 -> 9522 | H104: ='SCI 34 RUE HAUTE'!H104+'SCI LEGRAND'!H104+'SCI ARMEE ORIENT'!H104+'SCI CHENNEVIERES'!H104+'SCI TAVERNY'!H104+'SCI GENERAL JULES BRIMONT'!H104 -> 0
D105: DETTES FRS | E105: ='SCI 34 RUE HAUTE'!E105+'SCI LEGRAND'!E105+'SCI ARMEE ORIENT'!E105+'SCI CHENNEVIERES'!E105+'SCI TAVERNY'!E105+'SCI GENERAL JULES BRIMONT'!E105 -> 292643 | F105: ='SCI 34 RUE HAUTE'!F105+'SCI LEGRAND'!F105+'SCI ARMEE ORIENT'!F105+'SCI CHENNEVIERES'!F105+'SCI TAVERNY'!F105+'SCI GENERAL JULES BRIMONT'!F105 -> 48202 | G105: ='SCI 34 RUE HAUTE'!G105+'SCI LEGRAND'!G105+'SCI ARMEE ORIENT'!G105+'SCI CHENNEVIERES'!G105+'SCI TAVERNY'!G105+'SCI GENERAL JULES BRIMONT'!G105 -> 0 | H105: ='SCI 34 RUE HAUTE'!H105+'SCI LEGRAND'!H105+'SCI ARMEE ORIENT'!H105+'SCI CHENNEVIERES'!H105+'SCI TAVERNY'!H105+'SCI GENERAL JULES BRIMONT'!H105 -> 0
D106: DETTES FISCALES ET SOCIALES | E106: ='SCI 34 RUE HAUTE'!E106+'SCI LEGRAND'!E106+'SCI ARMEE ORIENT'!E106+'SCI CHENNEVIERES'!E106+'SCI TAVERNY'!E106+'SCI GENERAL JULES BRIMONT'!E106 -> 11075 | F106: ='SCI 34 RUE HAUTE'!F106+'SCI LEGRAND'!F106+'SCI ARMEE ORIENT'!F106+'SCI CHENNEVIERES'!F106+'SCI TAVERNY'!F106+'SCI GENERAL JULES BRIMONT'!F106 -> 12668 | G106: ='SCI 34 RUE HAUTE'!G106+'SCI LEGRAND'!G106+'SCI ARMEE ORIENT'!G106+'SCI CHENNEVIERES'!G106+'SCI TAVERNY'!G106+'SCI GENERAL JULES BRIMONT'!G106 -> 0 | H106: ='SCI 34 RUE HAUTE'!H106+'SCI LEGRAND'!H106+'SCI ARMEE ORIENT'!H106+'SCI CHENNEVIERES'!H106+'SCI TAVERNY'!H106+'SCI GENERAL JULES BRIMONT'!H106 -> 0
D107: AUTRES DETTES | E107: ='SCI 34 RUE HAUTE'!E107+'SCI LEGRAND'!E107+'SCI ARMEE ORIENT'!E107+'SCI CHENNEVIERES'!E107+'SCI TAVERNY'!E107+'SCI GENERAL JULES BRIMONT'!E107 -> 9809 | F107: ='SCI 34 RUE HAUTE'!F107+'SCI LEGRAND'!F107+'SCI ARMEE ORIENT'!F107+'SCI CHENNEVIERES'!F107+'SCI TAVERNY'!F107+'SCI GENERAL JULES BRIMONT'!F107 -> 18221 | G107: ='SCI 34 RUE HAUTE'!G107+'SCI LEGRAND'!G107+'SCI ARMEE ORIENT'!G107+'SCI CHENNEVIERES'!G107+'SCI TAVERNY'!G107+'SCI GENERAL JULES BRIMONT'!G107 -> 611 | H107: ='SCI 34 RUE HAUTE'!H107+'SCI LEGRAND'!H107+'SCI ARMEE ORIENT'!H107+'SCI CHENNEVIERES'!H107+'SCI TAVERNY'!H107+'SCI GENERAL JULES BRIMONT'!H107 -> 0
D109: VALORISATION DES BIENS | E109: =SUM(E110:E119) -> 0 | F109: =SUM(F110:F119) -> 0 | G109: =SUM(G110:G119) -> 0 | H109: =SUM(H110:H119) -> 0
D110: ESTIMATION A LA VALEUR DU MARCHE
D111: =D5 -> DEUIL LA BARRE Crèche | E111: 0 | F111: 0 | G111: 0
D112: =D6 -> DEUIL LA BARRE Ecole | E112: 0 | F112: 0 | G112: 0
D113: =D7 -> DEUIL LA BARRE Logements 1 appartement avec terrasse et jardin RDC | E113: 0 | F113: 0 | G113: 0
...

Sheet Emprunts
Y2: =V7-X7 -> 104903.87
B3: Nom prêt | C3: Société | D3: Banque | F3: N° cpte compta | G3: Montant prêt | I3: Date 1ere échéance | K3: 2020 | M3: 2021 | O3: 2022 | Q3: 2023 | S3: 2024 | U3: 2025 | W3: 2026 | Y3: 2027 | AA3: 2028 | AC3: 2029 | AE3: 2030 | AG3: 2031 | AI3: 2032 | AK3: 2033 | AM3: 2034 | AO3: 2035 | AQ3: 2036 | AS3: 2037 | AU3: 2038 | AW3: 2039 | AY3: 2040 | BA3: 2041 | BC3: 2042 | BE3: 2043
K4: Échéance (K+I) | L4: solde fin K | M4: Échéance | N4: solde fin | O4: Échéance | P4: solde fin | Q4: Échéance | R4: solde fin | S4: Échéance | T4: solde fin | U4: Échéance | V4: ="solde fin"&" "&U3 -> solde fin 2025 | W4: Échéance | X4: ="solde fin"&" "&W3 -> solde fin 2026 | Y4: Échéance | Z4: ="solde fin"&" "&Y3 -> solde fin 2027 | AA4: Échéance | AB4: ="solde fin"&" "&AA3 -> solde fin 2028 | AC4: Échéance | AD4: ="solde fin"&" "&AC3 -> solde fin 2029 | AE4: Échéance | AF4: ="solde fin"&" "&AE3 -> solde fin 2030 | AG4: Échéance | AH4: ="solde fin"&" "&AG3 -> solde fin 2031 | AI4: Échéance | AJ4: ="solde fin"&" "&AI3 -> solde fin 2032 | AK4: Échéance | AL4: ="solde fin"&" "&AK3 -> solde fin 2033 | AM4: Échéance | AN4: ="solde fin"&" "&AM3 -> solde fin 2034 | AO4: Échéance | AP4: ="solde fin"&" "&AO3 -> solde fin 2035 | AQ4: Échéance | AR4: ="solde fin"&" "&AQ3 -> solde fin 2036 | AS4: Échéance | AT4: ="solde fin"&" "&AS3 -> solde fin 2037 | AU4: Échéance | AV4: ="solde fin"&" "&AU3 -> solde fin 2038 | AW4: Échéance | AX4: ="solde fin"&" "&AW3 -> solde fin 2039 | AY4: Échéance | AZ4: ="solde fin"&" "&AY3 -> solde fin 2040 | BA4: Échéance | BB4: ="solde fin"&" "&BA3 -> solde fin 2041 | BC4: Échéance | BD4: ="solde fin"&" "&BC3 -> solde fin 2042 | BE4: Échéance | BF4: ="solde fin"&" "&BE3 -> solde fin 2043
B5: CE_SCI HOCHE | C5: 9-HOCHE | D5: CE | F5: 0 | G5: 435000 | H5: 0.013 | I5: 44140 | K5: 5488.74 | L5: 430451.3 | M5: 32932.44 | N5: 402951.25 | O5: 32932.44 | P5: 375091.57 | Q5: 32932.44 | R5: 346867.55 | S5: 32932.44 | T5: 318274.42 | U5: 319972.38 | V5: 0.0028812288 | W5: 0 | X5: 0 | Y5: 0 | Z5: 0 | AA5: 0 | AB5: 0 | AC5: 0 | AD5: 0 | AE5: 0 | AF5: 0 | AG5: 0 | AH5: 0 | AI5: 0 | AJ5: 0 | AK5: 0 | AL5: 0 | AM5: 0 | AN5: 0 | AO5: 0 | AP5: 0 | AQ5: 0 | AR5: 0 | AS5: 0 | AT5: 0 | AU5: 0 | AV5: 0 | AW5: 0 | AX5: 0 | AY5: 0 | AZ5: 0 | BA5: 0 | BB5: 0 | BC5: 0 | BD5: 0 | BE5: 0 | BF5: 0 | BH5: =(V5-X5)-U5 -> -319972.38
B6: CE_SCI 34 HAUTE | C6: 9-HAUTE | D6: CE | F6: 0 | G6: 409000 | H6: 0.0135 | I6: 44656 | K6: 0 | L6: 0 | M6: 0 | N6: 0 | O6: 24322.14 | P6: 388727.93 | Q6: 32429.52 | R6: 361377.42 | S6: 32429.52 | T6: 333655.38 | U6: 32429.52 | V6: 305556.77 | W6: 32429.52 | X6: 277076.48 | Y6: 32429.52 | Z6: 248209.31 | AA6: 32429.52 | AB6: 218950.01 | AC6: 32429.52 | AD6: 189293.27 | AE6: 32429.52 | AF6: 159234 | AG6: 32429.52 | AH6: 128766 | AI6: 32429.52 | AJ6: 97884 | AK6: 32429.52 | AL6: 66583 | AM6: 32429.52 | AN6: 34856 | AO6: 2698 | AP6: 0 | AQ6: 0 | AR6: 0 | AS6: 0 | AT6: 0 | AU6: 0 | AV6: 0 | AW6: 0 | AX6: 0 | AY6: 0 | AZ6: 0 | BA6: 0 | BB6: 0 | BC6: 0 | BD6: 0 | BE6: 0 | BF6: 0 | BH6: =(V6-X6)-U6 -> -3949.2239
B7: CE_SCI 34 HAUTE | C7: 9-HAUTE | D7: CE | F7: 220154G | G7: 1515000 | H7: 0.0135 | I7: 44814 | K7: 0 | L7: 0 | M7: 0 | N7: 0 | O7: 40041.28 | P7: 1481720.1 | Q7: 120123.84 | R7: 1380977.7 | S7: 120123.84 | T7: 1278866.8 | U7: 120123.84 | V7: 1175368.8 | W7: 120123.84 | X7: 1070464.9 | Y7: 120123.84 | Z7: 964136.04 | AA7: 120123.84 | AB7: 856362.81 | AC7: 120123.84 | AD7: 747125.61 | AE7: 120123.84 | AF7: 636405 | AG7: 120123.84 | AH7: 524179 | AI7: 120123.84 | AJ7: 410430 | AK7: 120123.84 | AL7: 295135 | AM7: 120123.84 | AN7: 178274 | AO7: =AM7 -> 120123.84 | AP7: 59826 | AQ7: 59826 | AR7: 0 | AS7: 0 | AT7: 0 | AU7: 0 | AV7: 0 | AW7: 0 | AX7: 0 | AY7: 0 | AZ7: 0 | BA7: 0 | BB7: 0 | BC7: 0 | BD7: 0 | BE7: 0 | BF7: 0 | BH7: =(V7-X7)-U7 -> -15219.967
B8: SG_SCI 34 HAUTE | C8: 9-HAUTE | D8: SG | F8: 225003100788 | G8: 350000 | H8: 0.0353 | I8: 45701 | K8: 0 | L8: 0 | M8: 0 | N8: 0 | O8: 0 | P8: 0 | Q8: 0 | R8: 0 | S8: 0 | T8: 0 | U8: 51796.03 | V8: 308928.85 | W8: 56504.76 | X8: 262584.23 | Y8: 56504.76 | Z8: 214576.92 | AA8: 56504.76 | AB8: 164847.26 | AC8: 56504.76 | AD8: 113333.46 | AE8: 56504.76 | AF8: 59972 | AG8: 56504.76 | AH8: 4965 | AI8: 4965 | AJ8: 0 | AK8: 0 | AM8: 0 | AO8: 0 | AQ8: 0 | AS8: 0 | AU8: 0 | AW8: 0 | AY8: 0 | BA8: 0 | BC8: 0 | BE8: 0 | BH8: =(V8-X8)-U8 -> -5451.413
B9: BNP_SCI LEGRAND | C9: 9-LEGRAND | D9: BNP | F9: 0 | G9: 239977.57 | H9: 0.01 | I9: 43118 | K9: 16504.968 | L9: 161724.07 | M9: 32775.176 | N9: 130422.67 | O9: 32462.162 | P9: 99121.27 | Q9: 32149.148 | R9: 67819.87 | S9: 31836.134 | T9: 36518.47 | U9: 31523.12 | V9: 5217.07 | W9: 5221.4176 | X9: 0 | Y9: 0 | Z9: 0 | AA9: 0 | AB9: 0 | AC9: 0 | AD9: 0 | AE9: 0 | AG9: 0 | AI9: 0 | AK9: 0 | AM9: 0 | AO9: 0 | AQ9: 0 | AS9: 0 | AU9: 0 | AW9: 0 | AY9: 0 | BA9: 0 | BC9: 0 | BE9: 0 | BH9: =(V9-X9)-U9 -> -26306.05
B10: BNP_SCI MADELI | C10: 9-MADELI | D10: BNP | F10: 0 | G10: 1600000 | H10: 0.015 | I10: 43101 | K10: 119182.66 | L10: 1308116.2 | M10: 119182.66 | N10: 1207868 | O10: 119182.66 | P10: 1106105.6 | Q10: 119182.66 | R10: 1002806.3 | S10: 1012529.9 | T10: 0 | U10: 0 | V10: 0 | W10: 0 | X10: 0 | Y10: 0 | Z10: 0 | AA10: 0 | AB10: 0 | AC10: 0 | AD10: 0 | AE10: 0 | AG10: 0 | AI10: 0 | AK10: 0 | AM10: 0 | AO10: 0 | AQ10: 0 | AS10: 0 | AU10: 0 | AW10: 0 | AY10: 0 | BA10: 0 | BC10: 0 | BE10: 0 | BH10: =(V10-X10)-U10 -> 0
B11: CE_SCI ARAGO | C11: 9-ARAGO | D11: CE | F11: 0 | G11: 1350000 | H11: 0.0208 | I11: 42883 | K11: 52744.22 | L11: 1004352.9 | M11: 105809.52 | N11: 918619.65 | O11: 105809.52 | P11: 831086.06 | Q11: 105809.52 | R11: 741714.32 | S11: 105809.52 | T11: 650465.82 | U11: 655361.05 | V11: 0 | W11: 0 | X11: 0 | Y11: 0 | Z11: 0 | AA11: 0 | AB11: 0 | AC11: 0 | AD11: 0 | AE11: 0 | AG11: 0 | AI11: 0 | AK11: 0 | AM11: 0 | AO11: 0 | AQ11: 0 | AS11: 0 | AU11: 0 | AW11: 0 | AY11: 0 | BA11: 0 | BC11: 0 | BE11: 0 | BH11: =(V11-X11)-U11 -> -655361.05
B12: SG_SCI LEGRAND | C12: 9-LEGRAND | D12: SG | F12: 0 | G12: 780000 | H12: 0.0189 | I12: 43315 | K12: 59759.48 | L12: 668774.53 | M12: 59759.48 | N12: 621244.57 | O12: 59759.48 | P12: 572808.46 | Q12: 59759.48 | R12: 523448.94 | S12: 59759.48 | T12: 473148.4 | U12: 59759.48 | V12: 421888.91 | W12: 59759.48 | X12: 369652.17 | Y12: 59759.48 | Z12: 316419.56 | AA12: 59759.48 | AB12: 262172.09 | AC12: 59759.48 | AD12: 206890.42 | AE12: 59759.48 | AF12: 150155 | AG12: 59759.48 | AH12: 93145 | AI12: 59759.48 | AJ12: 34641 | AK12: 34641 | AL12: 0 | BH12: =(V12-X12)-U12 -> -7522.7425
B13: CA_SCI ORIENT | C13: 9-ORIENT | D13: CA | F13: 0 | G13: 665000 | H13: 0.014 | I13: 45021 | K13: 0 | L13: 0 | M13: 0 | N13: 0 | O13: 0 | P13: 0 | Q13: 36706.58 | R13: 634929.09 | S13: 49252.44 | T13: 594305.65 | U13: 49252.44 | V13: 553109.81 | W13: 49252.44 | X13: 511333.52 | Y13: 49252.44 | Z13: 468968.6 | AA13: 49252.44 | AB13: 426006.74 | AC13: 49252.44 | AD13: 382439.55 | AE13: 49252.44 | AF13: 338258 | AG13: 49252.44 | AH13: 293455 | AI13: 49252.44 | AJ13: 248020 | AK13: 49252.44 | AL13: 201945 | AM13: 49252.44 | AN13: 155221 | AO13: 49252.44 | AP13: 107838 | AQ13: 49252.44 | AR13: 59788 | AS13: 49252.44 | AT13: 11061 | AU13: 11061 | AV13: 0 | BD13: 0 | BF13: 0 | BH13: =(V13-X13)-U13 -> -7476.1501
B14: LCL_SCI ORIENT | C14: 9-ORIENT | D14: LCL | F14: 0 | G14: 377612 | H14: 0.018 | I14: 44964 | K14: 0 | L14: 0 | M14: 0 | N14: 0 | O14: 0 | P14: 0 | Q14: 27140.52 | R14: 356544.55 | S14: 29607.84 | T14: 333162.23 | U14: 29607.84 | V14: 309355.54 | W14: 29607.84 | X14: 285116.78 | Y14: 29607.84 | Z14: 260438.11 | AA14: 29607.84 | AB14: 235311.53 | AC14: 29607.84 | AD14: 209728.93 | AE14: 29607.84 | AF14: 183682 | AG14: 29607.84 | AH14: 157162 | AI14: 29607.84 | AJ14: 130161 | AK14: 29607.84 | AL14: 102670 | AM14: 29607.84 | AN14: 74680 | AO14: 29607.84 | AP14: 46183 | AQ14: 29607.84 | AR14: 17167 | AS14: 17167 | AU14: 0 | AW14: 0 | AY14: 0 | BA14: 0 | BC14: 0 | BE14: 0 | BH14: =(V14-X14)-U14 -> -5369.0794
B15: LCL_SCI CHENNEVIERES | C15: 9-CHENNEVIERES | D15: LCL | F15: 23925728 | G15: 734000 | H15: 0.046 | I15: 45227 | K15: 0 | L15: 0 | M15: 0 | N15: 0 | O15: 0 | P15: 0 | Q15: 8441 | R15: 734000 | S15: 43173.23 | T15: 724590.77 | U15: 71400.92 | V15: 685859.27 | W15: 71400.92 | X15: 645315.16 | Y15: 71400.92 | Z15: 602873.59 | AA15: 71400.92 | AB15: 558445.78 | AC15: 71400.92 | AD15: 511938.77 | AE15: 71400.92 | AF15: 463255 | AG15: 71400.92 | AH15: 412293 | AI15: 71400.92 | AJ15: 358946 | AK15: 71400.92 | AL15: 303103 | AM15: 71400.92 | AN15: 244646 | AO15: 71400.92 | AP15: 183453 | AQ15: 71400.92 | AR15: 119397 | AS15: 71400.92 | AT15: 52342 | AU15: 52342 | BH15: =(V15-X15)-U15 -> -30856.805
B16: CE_SCI TAVERNY | C16: 9-TAVERNY | D16: CE | F16: 0 | G16: 1408923 | H16: 0.0493 | I16: 45327 | K16: 0 | L16: 0 | M16: 0 | N16: 0 | O16: 0 | P16: 0 | Q16: 0 | R16: 0 | S16: 60388.392 | T16: 1401718.1 | U16: 112600.56 | V16: 1357225.9 | W16: 112600.56 | X16: 1310489.9 | Y16: 112600.56 | Z16: 1261397 | AA16: 116055.93 | AB16: 1206315.7 | AC16: 117207.72 | AD16: 1147256.8 | AE16: 117207.72 | AF16: 1085219 | AG16: 117207.72 | AH16: 1020054 | AI16: 117207.72 | AJ16: 951602 | AK16: 117207.72 | AL16: 879698 | AM16: 117207.72 | AN16: 804167 | AO16: 117207.72 | AP16: 724828 | AQ16: 117207.72 | AR16: 641488 | AS16: 117207.72 | AT16: 553945 | AU16: 117207.72 | AV16: 461988 | AW16: 117207.72 | AX16: 381824 | AY16: 117207.72 | AZ16: 263927 | BA16: 117207.72 | BB16: 157343 | BC16: 117207.72 | BD16: 45385 | BE16: 45385 | BH16: =(V16-X16)-U16 -> -65864.577
B17: CE_SCI CHATOU | C17: 9-GJB | D17: CE | F17: 0 | G17: 1200000 | H17: 0.051 | I17: 45163 | K17: 0 | L17: 0 | M17: 0 | N17: 0 | O17: 0 | P17: 0 | Q17: 25500 | R17: 1200000 | S17: 110173.67 | T17: 1149972.3 | U17: 114625.82 | V17: 1092667.8 | W17: 114625.82 | X17: 1032371.6 | Y17: 114625.82 | Z17: 968927.37 | AA17: 114625.82 | AB17: 902170.75 | AC17: 114625.82 | AD17: 831928.82 | AE17: 114625.82 | AF17: 758020 | AG17: 114625.82 | AH17: 680252 | AI17: 114625.82 | AJ17: 598424 | AK17: 114625.82 | AL17: 512323 | AM17: 114625.82 | AN17: 421728 | AO17: 114625.82 | AP17: 326402 | AQ17: 114625.82 | AR17: 226100 | AS17: 114625.82 | AT17: 120561 | AU17: 114625.82 | AV17: 9512 | AW17: 9512 | BH17: =(V17-X17)-U17 -> -54329.586
B18: LCL_SCI PLESSIS | C18: 9-GJB | D18: LCL | F18: 0 | G18: 740000 | H18: 0.046 | I18: 45503 | K18: 0 | L18: 0 | M18: 0 | N18: 0 | O18: 0 | P18: 0 | Q18: 0 | R18: 0 | S18: 34193.058 | T18: 722661.52 | U18: 68386.117 | V18: 686767.34 | W18: 68386.117 | X18: 649186.77 | Y18: 68386.117 | Z18: 609840.57 | AA18: 68386.117 | AB18: 568645.79 | AC18: 68386.117 | AD18: 525515.59 | AE18: 68386.117 | AF18: 480359 | AG18: 68386.117 | AH18: 433081 | AI18: 68386.117 | AJ18: 383582 | AK18: 68386.117 | AL18: 331757 | AM18: 68386.117 | AN18: 277497 | AO18: 68386.117 | AP18: 220688 | AQ18: 68386.117 | AR18: 161209 | AS18: 68386.117 | AT18: 98937 | AU18: 68386.117 | AV18: 33739 | AW18: 33739 | BH18: =(V18-X18)-U18 -> -30805.542
B19: SG_SCI ALFORTVILLE | C19: 9-CHENNEVIERES | D19: SG | F19: 223326101166 | G19: 840000 | H19: 0.0453 | I19: 45275 | K19: 0 | L19: 0 | M19: 0 | N19: 0 | O19: 0 | P19: 0 | Q19: 3171 | R19: 840000 | S19: 41642.1 | T19: 836409.9 | U19: 81133.2 | V19: 792256.82 | W19: 81133.2 | X19: 746061.56 | Y19: 81133.2 | Z19: 697729.65 | AA19: 81133.2 | AB19: 647162.27 | AC19: 81133.2 | AD19: 594256.02 | AE19: 81133.2 | AF19: 538903 | AG19: 81133.2 | AH19: 480989 | AI19: 81133.2 | AJ19: 420397 | AK19: 81133.2 | AL19: 357002 | AM19: 81133.2 | AN19: 290675 | AO19: 81133.2 | AP19: 221281 | AQ19: 81133.2 | AR19: 148677 | AS19: 81133.2 | AT19: 72714 | AU19: 72714 | BH19: =(V19-X19)-U19 -> -34937.935
B20: LCL_900k | C20: AXORIEL | D20: LCL | F20: 0 | G20: 900000 | H20: 0.012 | I20: 44742 | K20: 0 | L20: 0 | M20: 0 | N20: 0 | O20: 134432.12 | P20: 775996.98 | Q20: 134432.12 | R20: 650501.46 | S20: 134432.12 | T20: 523495.48 | U20: 134432.12 | V20: 394960.85 | W20: 134432.12 | X20: 264879.18 | Y20: 134432.12 | Z20: 133231.84 | AA20: 134031.23 | AB20: 0 | AC20: 0 | AD20: 0 | AE20: 0 | AF20: 0 | AG20: 0 | AH20: 0 | AI20: 0 | AJ20: 0 | AK20: 0 | AL20: 0 | AM20: 0 | AN20: 0 | AO20: 0 | AP20: 0 | AQ20: 0 | AR20: 0 | AS20: 0 | AT20: 0 | AU20: 0 | AV20: 0 | AW20: 0 | AX20: 0 | AY20: 0 | AZ20: 0 | BA20: 0 | BB20: 0 | BC20: 0 | BD20: 0 | BE20: 0 | BF20: 0 | BH20: =(V20-X20)-U20 -> -4350.4524
B21: LCL_900k | C21: HIO | D21: LCL | F21: 0 | G21: 900000 | H21: 0.012 | I21: 44742 | K21: 0 | L21: 0 | M21: 0 | N21: 0 | O21: 134432.12 | P21: 775996.98 | Q21: 134432.12 | R21: 650501.46 | S21: 134432.12 | T21: 523495.48 | U21: 134432.12 | V21: 394960.85 | W21: 134432.12 | X21: 264879.18 | Y21: 134432.12 | Z21: 133231.84 | AA21: 134031.23 | AB21: 0 | AC21: 0 | AD21: 0 | AE21: 0 | AF21: 0 | AG21: 0 | AH21: 0 | AI21: 0 | AJ21: 0 | AK21: 0 | AL21: 0 | AM21: 0 | AN21: 0 | AO21: 0 | AP21: 0 | AQ21: 0 | AR21: 0 | AS21: 0 | AT21: 0 | AU21: 0 | AV21: 0 | AW21: 0 | AX21: 0 | AY21: 0 | AZ21: 0 | BA21: 0 | BB21: 0 | BC21: 0 | BD21: 0 | BE21: 0 | BF21: 0 | BH21: =(V21-X21)-U21 -> -4350.4524
B22: BNP_793k | C22: AXORIEL | D22: BNP | F22: 0 | G22: 793000 | H22: 0.00781 | I22: 43637 | K22: 120019.13 | L22: 679714.29 | M22: 119134.36 | N22: 566428.59 | O22: 119457.23 | P22: 453142.89 | Q22: 130182.54 | R22: 339857.18 | S22: 128413.04 | T22: 226571.5 | U22: 122954.35 | V22: 113285.79 | W22: 117674.14 | X22: 0 | Y22: 0 | Z22: 0 | AA22: 0 | AB22: 0 | AC22: 0 | AD22: 0 | AE22: 0 | AF22: 0 | AG22: 0 | AH22: 0 | AI22: 0 | AJ22: 0 | AK22: 0 | AL22: 0 | AM22: 0 | AN22: 0 | AO22: 0 | AP22: 0 | AQ22: 0 | AR22: 0 | AS22: 0 | AT22: 0 | AU22: 0 | AV22: 0 | AW22: 0 | AX22: 0 | AY22: 0 | AZ22: 0 | BA22: 0 | BB22: 0 | BC22: 0 | BD22: 0 | BE22: 0 | BF22: 0 | BH22: =(V22-X22)-U22 -> -9668.5641
B23: BNP_793k | C23: HIO | D23: BNP | F23: 0 | G23: 793000 | H23: 0.00781 | I23: 43637 | K23: 120019.13 | L23: 679714.29 | M23: 119134.36 | N23: 566428.59 | O23: 119457.23 | P23: 453142.89 | Q23: 130182.54 | R23: 339857.18 | S23: 128413.04 | T23: 226571.5 | U23: 122954.35 | V23: 113285.79 | W23: 117674.14 | X23: 0 | Y23: 0 | Z23: 0 | AA23: 0 | AB23: 0 | AC23: 0 | AD23: 0 | AE23: 0 | AF23: 0 | AG23: 0 | AH23: 0 | AI23: 0 | AJ23: 0 | AK23: 0 | AL23: 0 | AM23: 0 | AN23: 0 | AO23: 0 | AP23: 0 | AQ23: 0 | AR23: 0 | AS23: 0 | AT23: 0 | AU23: 0 | AV23: 0 | AW23: 0 | AX23: 0 | AY23: 0 | AZ23: 0 | BA23: 0 | BB23: 0 | BC23: 0 | BD23: 0 | BE23: 0 | BF23: 0 | BH23: =(V23-X23)-U23 -> -9668.5641
G24: 16030513 | K24: 493718.33 | L24: 4932847.6 | M24: 588728 | N24: 4413963.3 | O24: 922288.39 | P24: 7312940.8 | Q24: 1132575 | R24: 10171203 | S24: 2289541.8 | T24: 10353884 | U24: 2312745.3 | V24: 8710696.1 | W24: 1305258.4 | X24: 7689411.4 | Y24: 1064688.7 | Z24: 6879980.4 | AA24: 1067342.3 | AB24: 6046390.8 | AC24: 800431.65 | AD24: 5459707.2 | AE24: 800431.65 | AF24: 5459707.2 | AG24: 800431.65 | AH24: 5459707.2 | AI24: 800431.65 | AJ24: 5459707.2 | AK24: 800431.65 | AL24: 5459707.2 | AM24: 800431.65 | AN24: 5459707.2 | AO24: 800431.65 | AP24: 5459707.2 | AQ24: 800431.65 | AR24: 5459707.2 | AS24: 800431.65 | AT24: 5459707.2 | AU24: 800431.65 | AV24: 5459707.2 | AW24: 800431.65 | AX24: 5459707.2 | AY24: 800431.65 | AZ24: 5459707.2 | BA24: 800431.65 | BB24: 5459707.2 | BC24: 800431.65 | BD24: 5459707.2 | BE24: 800431.65 | BF24: 5459707.2 | BH24: =(V24-X24)-U24 -> -1291460.5
